[
{"price": ["\n$829,900\n", "\n$1,999,999\n", "\n$659,900\n", "\n$875,000\n", "\n$2,559,900\n", "\n$900,000\n", "\n$479,000\n", "\n$1,419,000\n", "\n$2,595,000\n", "\n$3,200,000\n", "\n$2,095,000\n", "\n$769,888\n", "\n$889,000\n", "\n$1,998,000\n", "\n$619,900\n", "\n$879,000\n", "\n$1,129,000\n", "\n$528,000\n", "\n$419,900\n", "\n$889,000\n", "\n$1,949,000\n", "\n$845,000\n"], "addr": ["28 Medley Crescent, Toronto, ON, M1J 1Y3", "67 Sylvan Avenue, Toronto, ON, M1M 1J9", "329-7 Kenaston Gardens, Toronto, ON, M2K 0E9", "92 Dutch Myrtle Way, Toronto, ON, M3B 3K8", "125 Brighton Avenue, Toronto, ON, M3H 4C9", "126 Meandering Tr, Toronto, ON, M1B 6E4", "115-1040 The Queensway Avenue, Toronto, ON, M8Z 0A7", "62A Pitt Avenue, Toronto, ON, M1L 2R4", "106 King High Avenue, Toronto, ON, M3H 3B1", "2B Carluke Crescent, Toronto, ON, M2L 2V4", "268 Bain Avenue, Toronto, ON, M4K 1G3", "804-633 Bay Street, Toronto, ON, M5G 2G4", "63 Oak Park Avenue, Toronto, ON, M4C 4M2", "32 Wilmar Road, Toronto, ON, M9B 3R9", "S1104-120 Bayview Avenue, Toronto, ON, M5A 3R7", "23 Wolfe Avenue, Toronto, ON, M1K 3M2", "57 Thirtieth Street, Toronto, ON, M8W 3B7", "417-116 George Street, Toronto, ON, M5A 3S9", "1403-20 Edgecliff Gfwy, Toronto, ON, M3C 3A4", "103-2010 Islington Avenue, Toronto, ON, M9P 3S8", "5 Broadmead Avenue, Toronto, ON, M1M 1C3", "515 Northcliffe Boulevard, Toronto, ON, M6E 3L4"], "link": ["/properties/E4546454/28-medley-crescent-toronto-on?search_id=toronto-on&search_type=property_browse", "/properties/E4513401/67-sylvan-avenue-toronto-on?search_id=toronto-on&search_type=property_browse", "/properties/C4577373/329-7-kenaston-gardens-toronto-on?search_id=toronto-on&search_type=property_browse", "/properties/C4576283/92-dutch-myrtle-way-toronto-on?search_id=toronto-on&search_type=property_browse", "/properties/C4575428/125-brighton-avenue-toronto-on?search_id=toronto-on&search_type=property_browse", "/properties/E4572703/126-meandering-tr-toronto-on?search_id=toronto-on&search_type=property_browse", "/properties/W4572169/115-1040-the-queensway-avenue-toronto-on?search_id=toronto-on&search_type=property_browse", "/properties/E4572117/62a-pitt-avenue-toronto-on?search_id=toronto-on&search_type=property_browse", "/properties/C4572122/106-king-high-avenue-toronto-on?search_id=toronto-on&search_type=property_browse", "/properties/C4571886/2b-carluke-crescent-toronto-on?search_id=toronto-on&search_type=property_browse", "/properties/E4571665/268-bain-avenue-toronto-on?search_id=toronto-on&search_type=property_browse", "/properties/C4571503/804-633-bay-street-toronto-on?search_id=toronto-on&search_type=property_browse", "/properties/E4571402/63-oak-park-avenue-toronto-on?search_id=toronto-on&search_type=property_browse", "/properties/W4571200/32-wilmar-road-toronto-on?search_id=toronto-on&search_type=property_browse", "/properties/C4568121/1104-120-s-bayview-avenue-toronto-on?search_id=toronto-on&search_type=property_browse", "/properties/E4567281/23-wolfe-avenue-toronto-on?search_id=toronto-on&search_type=property_browse", "/properties/W4565193/57-thirtieth-street-toronto-on?search_id=toronto-on&search_type=property_browse", "/properties/C4564078/417-116-george-street-toronto-on?search_id=toronto-on&search_type=property_browse", "/properties/C4559608/1403-20-edgecliff-gfwy-toronto-on?search_id=toronto-on&search_type=property_browse", "/properties/W4557479/103-2010-islington-avenue-toronto-on?search_id=toronto-on&search_type=property_browse", "/properties/E4554867/5-broadmead-avenue-toronto-on?search_id=toronto-on&search_type=property_browse", "/properties/C4554650/515-northcliffe-boulevard-toronto-on?search_id=toronto-on&search_type=property_browse"]},
{"price": ["\n$1,999,999\n", "\n$1,129,000\n", "\n$1,285,000\n", "\n$799,990\n", "\n$410,000\n", "\n$479,900\n", "\n$799,000\n", "\n$548,880\n", "\n$799,900\n", "\n$395,000\n", "\n$748,500\n", "\n$488,800\n", "\n$799,000\n", "\n$895,000\n", "\n$808,888\n", "\n$928,000\n", "\n$449,000\n", "\n$2,249,888\n", "\n$1,449,000\n", "\n$410,000\n", "\n$448,000\n", "\n$540,000\n"], "addr": ["67 Sylvan Avenue, Toronto, ON, M1M 1J9", "57 Thirtieth Street, Toronto, ON, M8W 3B7", "73 Cannon Road, Toronto, ON, M8Y 1S2", "4608-20 Shore Breeze Drive, Toronto, ON, M8V 0C7", "1508-1 Lee Centre Drive, Toronto, ON, M1H 3J2", "1519-135 Village Green Square, Toronto, ON, M1S 0G4", "Toronto, ON", "513-228 Bonis Avenue, Toronto, ON, M1T 3W4", "35 Princeway Drive, Toronto, ON, M1R 2V8", "1207-1 Massey Square, Toronto, ON, M4C 5L4", "2101-1 Rean Drive, Toronto, ON, M2K 3C1", "808-160 Vanderhoof Avenue, Toronto, ON, M4G 0B7", "14 Alpha Avenue, Toronto, ON, M4X 1J3", "106-3800 Yonge Street, Toronto, ON, M4N 3P7", "1405-390 Cherry Street, Toronto, ON, M5A 3L7", "2303-218 W Queens Quay, Toronto, ON, M5J 2Y6", "909-280 Donlands Avenue, Toronto, ON, M4J 3R4", "4306-15 Iceboat Terrace, Toronto, ON, M5V 4A5", "34 Deanewood Crescent, Toronto, ON, M9B 3B1", "1106-3559 Eglinton Avenue, Toronto, ON, M6M 5C6", "512-17 Zorra Street, Toronto, ON, M8Z 4Z6", "54-50 Blackwell Avenue, Toronto, ON, M1B 1K2"], "link": ["/properties/E4513401/67-sylvan-avenue-toronto-on?page=18&search_id=toronto-on&search_type=property_browse", "/properties/W4565193/57-thirtieth-street-toronto-on?page=18&search_id=toronto-on&search_type=property_browse", "/properties/W4574216/73-cannon-road-toronto-on?page=18&search_id=toronto-on&search_type=property_browse", "/properties/W4574184/4608-20-shore-breeze-drive-toronto-on?page=18&search_id=toronto-on&search_type=property_browse", "/properties/E4574186/1508-1-lee-centre-drive-toronto-on?page=18&search_id=toronto-on&search_type=property_browse", "/properties/E4574208/1519-135-village-green-square-toronto-on?page=18&search_id=toronto-on&search_type=property_browse", "/properties/E4574207/toronto-on?page=18&search_id=toronto-on&search_type=property_browse", "/properties/E4574236/513-228-bonis-avenue-toronto-on?page=18&search_id=toronto-on&search_type=property_browse", "/properties/E4574189/35-princeway-drive-toronto-on?page=18&search_id=toronto-on&search_type=property_browse", "/properties/E4574287/1207-1-massey-square-toronto-on?page=18&search_id=toronto-on&search_type=property_browse", "/properties/C4574230/2101-1-rean-drive-toronto-on?page=18&search_id=toronto-on&search_type=property_browse", "/properties/C4574260/808-160-vanderhoof-avenue-toronto-on?page=18&search_id=toronto-on&search_type=property_browse", "/properties/C4574215/14-alpha-avenue-toronto-on?page=18&search_id=toronto-on&search_type=property_browse", "/properties/C4574256/106-3800-yonge-street-toronto-on?page=18&search_id=toronto-on&search_type=property_browse", "/properties/C4574240/1405-390-cherry-street-toronto-on?page=18&search_id=toronto-on&search_type=property_browse", "/properties/C4574185/2303-218-w-queens-quay-toronto-on?page=18&search_id=toronto-on&search_type=property_browse", "/properties/E4573378/909-280-donlands-avenue-toronto-on?page=18&search_id=toronto-on&search_type=property_browse", "/properties/C4571998/4306-15-iceboat-terrace-toronto-on?page=18&search_id=toronto-on&search_type=property_browse", "/properties/W4574020/34-deanewood-crescent-toronto-on?page=18&search_id=toronto-on&search_type=property_browse", "/properties/W4574100/1106-3559-eglinton-avenue-toronto-on?page=18&search_id=toronto-on&search_type=property_browse", "/properties/W4574126/512-17-zorra-street-toronto-on?page=18&search_id=toronto-on&search_type=property_browse", "/properties/E4574028/54-50-blackwell-avenue-toronto-on?page=18&search_id=toronto-on&search_type=property_browse"]},
{"price": ["\n$1,999,999\n", "\n$829,900\n", "\n$699,900\n", "\n$529,000\n", "\n$1,759,000\n", "\n$574,900\n", "\n$3,088,000\n", "\n$1,149,000\n", "\n$749,000\n", "\n$398,000\n", "\n$436,000\n", "\n$999,000\n", "\n$2,899,999\n", "\n$799,000\n", "\n$1,200,000\n", "\n$1,999,000\n", "\n$749,900\n", "\n$849,000\n", "\n$3,595,000\n", "\n$1,349,900\n", "\n$998,000\n", "\n$699,000\n"], "addr": ["67 Sylvan Avenue, Toronto, ON, M1M 1J9", "28 Medley Crescent, Toronto, ON, M1J 1Y3", "128-2320 E Gerrard Street, Toronto, ON, M4E 2E1", "Ph 111-330 Alton Towers Circ, Toronto, ON, M1V 5H3", "668 Greenwood Avenue, Toronto, ON, M4J 4B5", "109-5 Richgrove Drive, Toronto, ON, M9R 0A3", "271 Ellerslie Avenue, Toronto, ON, M2R 1B6", "421 Glenlake Avenue, Toronto, ON, M6P 1G5", "1405-100 Quebec Avenue, Toronto, ON, M6P 4B8", "1403-238 Albion Road, Toronto, ON, M9W 6A7", "205-3 Michael Power Place, Toronto, ON, M9A 0A2", "17 Walford Road, Toronto, ON, M8X 2P2", "34 Oak Hampton Boulevard, Toronto, ON, M9A 2V1", "41 W Bow Valley Drive, Toronto, ON, M1G 3J4", "239 Conlins Road, Toronto, ON, M1C 1C4", "46 Virginia Avenue, Toronto, ON, M4C 2S7", "15 Northview Avenue, Toronto, ON, M1N 1V9", "65 Lawson Road, Toronto, ON, M1C 2J2", "585 Brookdale Avenue, Toronto, ON, M5M 1S3", "39 Minto Street, Toronto, ON, M4L 1B5", "9-255 Van Dusen Boulevard, Toronto, ON, M8Z 3J2", "504-260 Scarlett Road, Toronto, ON, M6N 4X6"], "link": ["/properties/E4513401/67-sylvan-avenue-toronto-on?page=21&search_id=toronto-on&search_type=property_browse", "/properties/E4546454/28-medley-crescent-toronto-on?page=21&search_id=toronto-on&search_type=property_browse", "/properties/E4573813/128-2320-e-gerrard-street-toronto-on?page=21&search_id=toronto-on&search_type=property_browse", "/properties/E4573701/ph-111-330-alton-towers-circ-toronto-on?page=21&search_id=toronto-on&search_type=property_browse", "/properties/E4573697/668-greenwood-avenue-toronto-on?page=21&search_id=toronto-on&search_type=property_browse", "/properties/W4573681/109-5-richgrove-drive-toronto-on?page=21&search_id=toronto-on&search_type=property_browse", "/properties/C4573710/271-ellerslie-avenue-toronto-on?page=21&search_id=toronto-on&search_type=property_browse", "/properties/W4573631/421-glenlake-avenue-toronto-on?page=21&search_id=toronto-on&search_type=property_browse", "/properties/W4573619/1405-100-quebec-avenue-toronto-on?page=21&search_id=toronto-on&search_type=property_browse", "/properties/W4573565/1403-238-albion-road-toronto-on?page=21&search_id=toronto-on&search_type=property_browse", "/properties/W4573518/205-3-michael-power-place-toronto-on?page=21&search_id=toronto-on&search_type=property_browse", "/properties/W4573483/17-walford-road-toronto-on?page=21&search_id=toronto-on&search_type=property_browse", "/properties/W4573504/34-oak-hampton-boulevard-toronto-on?page=21&search_id=toronto-on&search_type=property_browse", "/properties/E4573636/41-w-bow-valley-drive-toronto-on?page=21&search_id=toronto-on&search_type=property_browse", "/properties/E4573525/239-conlins-road-toronto-on?page=21&search_id=toronto-on&search_type=property_browse", "/properties/E4573575/46-virginia-avenue-toronto-on?page=21&search_id=toronto-on&search_type=property_browse", "/properties/E4573541/15-northview-avenue-toronto-on?page=21&search_id=toronto-on&search_type=property_browse", "/properties/E4573510/65-lawson-road-toronto-on?page=21&search_id=toronto-on&search_type=property_browse", "/properties/C4573491/585-brookdale-avenue-toronto-on?page=21&search_id=toronto-on&search_type=property_browse", "/properties/E4573501/39-minto-street-toronto-on?page=21&search_id=toronto-on&search_type=property_browse", "/properties/W4573465/9-255-van-dusen-boulevard-toronto-on?page=21&search_id=toronto-on&search_type=property_browse", "/properties/W4573458/504-260-scarlett-road-toronto-on?page=21&search_id=toronto-on&search_type=property_browse"]},
{"price": ["\n$1,999,999\n", "\n$1,129,000\n", "\n$429,900\n", "\n$699,000\n", "\n$799,900\n", "\n$998,000\n", "\n$699,800\n", "\n$885,000\n", "\n$599,000\n", "\n$798,000\n", "\n$1,499,000\n", "\n$1,249,000\n", "\n$848,000\n", "\n$1,149,000\n", "\n$829,000\n", "\n$578,000\n", "\n$648,000\n", "\n$489,000\n", "\n$469,990\n", "\n$698,000\n", "\n$768,000\n", "\n$729,900\n"], "addr": ["67 Sylvan Avenue, Toronto, ON, M1M 1J9", "57 Thirtieth Street, Toronto, ON, M8W 3B7", "55-130 Ling Road, Toronto, ON, M1E 4V9", "73 Murray Glen Drive, Toronto, ON, M1R 3K1", "125 Torrens Avenue, Toronto, ON, M4J 2P6", "65 Scoville Square, Toronto, ON, M1V 5L9", "56 Tansley Avenue, Toronto, ON, M1J 1P3", "14 Elmsdale Road, Toronto, ON, M4J 3M4", "475 Dawes Road, Toronto, ON, M4B 2E9", "239 Fairglen Avenue, Toronto, ON, M1W 1A9", "330 Woodmount Avenue, Toronto, ON, M4C 4A3", "31 Gledhill Avenue, Toronto, ON, M4C 5K7", "1511-98 Mcgill Street, Toronto, ON, M5B 0B1", "1004-224 W King Street, Toronto, ON, M5V 1H8", "715-60 Berwick Avenue, Toronto, ON, M5P 0A3", "Ph04-70 Temperance Street, Toronto, ON, M5H 4E8", "1805-21 Widmer Street, Toronto, ON, M5V 2E8", "408-18 Valley Woods Road, Toronto, ON, M3A 0A1", "505-2756 Old Leslie Street, Toronto, ON, M2K 0E2", "1705-88 Harbour Street, Toronto, ON, M5J 0C3", "5405-50 E Charles Street, Toronto, ON, M4Y 1T1", "708-28 Linden Street, Toronto, ON, M4Y 0A4"], "link": ["/properties/E4513401/67-sylvan-avenue-toronto-on?page=23&search_id=toronto-on&search_type=property_browse", "/properties/W4565193/57-thirtieth-street-toronto-on?page=23&search_id=toronto-on&search_type=property_browse", "/properties/E4573407/55-130-ling-road-toronto-on?page=23&search_id=toronto-on&search_type=property_browse", "/properties/E4573358/73-murray-glen-drive-toronto-on?page=23&search_id=toronto-on&search_type=property_browse", "/properties/E4573392/125-torrens-avenue-toronto-on?page=23&search_id=toronto-on&search_type=property_browse", "/properties/E4573294/65-scoville-square-toronto-on?page=23&search_id=toronto-on&search_type=property_browse", "/properties/E4573218/56-tansley-avenue-toronto-on?page=23&search_id=toronto-on&search_type=property_browse", "/properties/E4573191/14-elmsdale-road-toronto-on?page=23&search_id=toronto-on&search_type=property_browse", "/properties/E4573186/475-dawes-road-toronto-on?page=23&search_id=toronto-on&search_type=property_browse", "/properties/E4573122/239-fairglen-avenue-toronto-on?page=23&search_id=toronto-on&search_type=property_browse", "/properties/E4573061/330-woodmount-avenue-toronto-on?page=23&search_id=toronto-on&search_type=property_browse", "/properties/E4573043/31-gledhill-avenue-toronto-on?page=23&search_id=toronto-on&search_type=property_browse", "/properties/C4573467/1511-98-mcgill-street-toronto-on?page=23&search_id=toronto-on&search_type=property_browse", "/properties/C4573443/1004-224-w-king-street-toronto-on?page=23&search_id=toronto-on&search_type=property_browse", "/properties/C4573408/715-60-berwick-avenue-toronto-on?page=23&search_id=toronto-on&search_type=property_browse", "/properties/C4573404/ph04-70-temperance-street-toronto-on?page=23&search_id=toronto-on&search_type=property_browse", "/properties/C4573396/1805-21-widmer-street-toronto-on?page=23&search_id=toronto-on&search_type=property_browse", "/properties/C4573343/408-18-valley-woods-road-toronto-on?page=23&search_id=toronto-on&search_type=property_browse", "/properties/C4573354/505-2756-old-leslie-street-toronto-on?page=23&search_id=toronto-on&search_type=property_browse", "/properties/C4573355/1705-88-harbour-street-toronto-on?page=23&search_id=toronto-on&search_type=property_browse", "/properties/C4573336/5405-50-e-charles-street-toronto-on?page=23&search_id=toronto-on&search_type=property_browse", "/properties/C4573292/708-28-linden-street-toronto-on?page=23&search_id=toronto-on&search_type=property_browse"]},
{"price": ["\n$829,900\n", "\n$1,129,000\n", "\n$849,000\n", "\n$834,900\n", "\n$1,099,900\n", "\n$1,099,900\n", "\n$1,299,900\n", "\n$390,000\n", "\n$627,800\n", "\n$625,000\n", "\n$8,998,000\n", "\n$459,900\n", "\n$3,188,000\n", "\n$678,000\n", "\n$858,900\n", "\n$239,900\n", "\n$434,901\n", "\n$385,000\n", "\n$319,900\n", "\n$1,268,000\n", "\n$999,000\n", "\n$1,288,000\n"], "addr": ["28 Medley Crescent, Toronto, ON, M1J 1Y3", "57 Thirtieth Street, Toronto, ON, M8W 3B7", "32 Runnymede Road, Toronto, ON, M6S 2Y2", "30 Ellins Avenue, Toronto, ON, M6N 2A3", "121 Harding Boulevard, Toronto, ON, M1N 3E1", "123 Harding Boulevard, Toronto, ON, M1N 3E1", "8 Sugar Bush Square, Toronto, ON, M1C 3M7", "1506-1470 Midland Avenue, Toronto, ON, M1P 4Z4", "723-5 Everson Drive, Toronto, ON, M2N 7C3", "3218-5 E Sheppard Avenue, Toronto, ON, M2N 2Z8", "88 Plymbridge Road, Toronto, ON, M2P 1A3", "1003-30 Gloucester Street, Toronto, ON, M4Y 1L6", "19 Magpie Crescent, Toronto, ON, M2L 2E6", "944-15 Merchants' Wharf Street, Toronto, ON, M5A 0N8", "903-111 W St Clair Avenue, Toronto, ON, M4V 1N5", "1208-3390 Weston Road, Toronto, ON, M9M 2X3", "503-5 Rowntree Road, Toronto, ON, M9V 5G9", "1910-400 Mclevin Avenue, Toronto, ON, M1B 5J4", "34-40 Rexdale Boulevard, Toronto, ON, M9W 5Z3", "1 Cardigan Road, Toronto, ON, M8Z 2V8", "19 Walford Road, Toronto, ON, M8X 2P2", "108 Westbury Crescent, Toronto, ON, M6M 1M5"], "link": ["/properties/E4546454/28-medley-crescent-toronto-on?page=19&search_id=toronto-on&search_type=property_browse", "/properties/W4565193/57-thirtieth-street-toronto-on?page=19&search_id=toronto-on&search_type=property_browse", "/properties/W4574022/32-runnymede-road-toronto-on?page=19&search_id=toronto-on&search_type=property_browse", "/properties/W4573054/30-ellins-avenue-toronto-on?page=19&search_id=toronto-on&search_type=property_browse", "/properties/E4574103/121-harding-boulevard-toronto-on?page=19&search_id=toronto-on&search_type=property_browse", "/properties/E4574077/123-harding-boulevard-toronto-on?page=19&search_id=toronto-on&search_type=property_browse", "/properties/E4574006/8-sugar-bush-square-toronto-on?page=19&search_id=toronto-on&search_type=property_browse", "/properties/E4574115/1506-1470-s-midland-avenue-toronto-on?page=19&search_id=toronto-on&search_type=property_browse", "/properties/C4574058/723-5-everson-drive-toronto-on?page=19&search_id=toronto-on&search_type=property_browse", "/properties/C4574065/3218-5-e-sheppard-avenue-toronto-on?page=19&search_id=toronto-on&search_type=property_browse", "/properties/C4574080/88-plymbridge-road-toronto-on?page=19&search_id=toronto-on&search_type=property_browse", "/properties/C4574002/1003-30-gloucester-street-toronto-on?page=19&search_id=toronto-on&search_type=property_browse", "/properties/C4574059/19-magpie-crescent-toronto-on?page=19&search_id=toronto-on&search_type=property_browse", "/properties/C4574128/944-15-merchants-wharf-street-toronto-on?page=19&search_id=toronto-on&search_type=property_browse", "/properties/C4573991/903-111-w-st-clair-avenue-toronto-on?page=19&search_id=toronto-on&search_type=property_browse", "/properties/W4572554/1208-3390-weston-road-toronto-on?page=19&search_id=toronto-on&search_type=property_browse", "/properties/W4571570/503-5-rowntree-road-toronto-on?page=19&search_id=toronto-on&search_type=property_browse", "/properties/E4571732/1910-400-mclevin-avenue-toronto-on?page=19&search_id=toronto-on&search_type=property_browse", "/properties/W4573966/34-40-rexdale-boulevard-toronto-on?page=19&search_id=toronto-on&search_type=property_browse", "/properties/W4573855/1-cardigan-road-toronto-on?page=19&search_id=toronto-on&search_type=property_browse", "/properties/W4573946/19-walford-road-toronto-on?page=19&search_id=toronto-on&search_type=property_browse", "/properties/W4573905/108-westbury-crescent-toronto-on?page=19&search_id=toronto-on&search_type=property_browse"]},
{"price": ["\n$1,999,999\n", "\n$829,900\n", "\n$1,895,000\n", "\n$2,285,000\n", "\n$1,050,000\n", "\n$924,800\n", "\n$699,000\n", "\n$635,000\n", "\n$615,000\n", "\n$1,088,000\n", "\n$2,795,000\n", "\n$938,000\n", "\n$11,800,000\n", "\n$585,000\n", "\n$2,580,000\n", "\n$829,000\n", "\n$949,000\n", "\n$1,028,000\n", "\n$678,000\n", "\n$2,195,000\n", "\n$1,288,000\n", "\n$579,000\n"], "addr": ["67 Sylvan Avenue, Toronto, ON, M1M 1J9", "28 Medley Crescent, Toronto, ON, M1J 1Y3", "595 Castlefield Avenue, Toronto, ON, M5N 1L9", "19 Farrell Avenue, Toronto, ON, M2R 1C7", "203-170 Avenue Road, Toronto, ON, M5R 0A4", "1127-500 Doris Avenue, Toronto, ON, M2N 0C1", "98 Clovelly Avenue, Toronto, ON, M6E 2E6", "703-39 Brant Street, Toronto, ON, M5V 2L9", "2801-155 Yorkville Avenue, Toronto, ON, M5R 1C4", "Lrg 07-7 Lorraine Drive, Toronto, ON, M2N 7H2", "267 Brooke Avenue, Toronto, ON, M5M 2L1", "908-550 Queens Quay West Quay, Toronto, ON, M5V 3M8", "75 Highland Crescent, Toronto, ON, M2L 1G7", "523-1210 Don Mills Road, Toronto, ON, M3B 3N8", "30 Orchid Court, Toronto, ON, M2L 2X8", "47-110 George Henry Boulevard, Toronto, ON, M2J 1E7", "1403-12 Sudbury Street, Toronto, ON, M6J 3W7", "Ph106-35 Hollywood Avenue, Toronto, ON, M2N 0A9", "401-270 Rushton Road, Toronto, ON, M6C 1B4", "#th 5-290 W St Clair Avenue, Toronto, ON, M4V 1S3", "399 Woburn Avenue, Toronto, ON, M5M 1L4", "2601-23 Hollywood Avenue, Toronto, ON, M2N 7L8"], "link": ["/properties/E4513401/67-sylvan-avenue-toronto-on?page=24&search_id=toronto-on&search_type=property_browse", "/properties/E4546454/28-medley-crescent-toronto-on?page=24&search_id=toronto-on&search_type=property_browse", "/properties/C4573267/595-castlefield-avenue-toronto-on?page=24&search_id=toronto-on&search_type=property_browse", "/properties/C4573309/19-farrell-avenue-toronto-on?page=24&search_id=toronto-on&search_type=property_browse", "/properties/C4573277/203-170-avenue-road-toronto-on?page=24&search_id=toronto-on&search_type=property_browse", "/properties/C4573255/1127-500-doris-avenue-toronto-on?page=24&search_id=toronto-on&search_type=property_browse", "/properties/C4573254/98-clovelly-avenue-toronto-on?page=24&search_id=toronto-on&search_type=property_browse", "/properties/C4573261/703-39-brant-street-toronto-on?page=24&search_id=toronto-on&search_type=property_browse", "/properties/C4573205/2801-155-yorkville-avenue-toronto-on?page=24&search_id=toronto-on&search_type=property_browse", "/properties/C4573246/lrg-07-7-lorraine-drive-toronto-on?page=24&search_id=toronto-on&search_type=property_browse", "/properties/C4573237/267-brooke-avenue-toronto-on?page=24&search_id=toronto-on&search_type=property_browse", "/properties/C4573145/908-550-queens-quay-west-quay-toronto-on?page=24&search_id=toronto-on&search_type=property_browse", "/properties/C4573175/75-highland-crescent-toronto-on?page=24&search_id=toronto-on&search_type=property_browse", "/properties/C4573200/523-1210-don-mills-road-toronto-on?page=24&search_id=toronto-on&search_type=property_browse", "/properties/C4573185/30-orchid-court-toronto-on?page=24&search_id=toronto-on&search_type=property_browse", "/properties/C4573137/47-110-george-henry-boulevard-toronto-on?page=24&search_id=toronto-on&search_type=property_browse", "/properties/C4573140/1403-12-sudbury-street-toronto-on?page=24&search_id=toronto-on&search_type=property_browse", "/properties/C4573143/ph106-35-hollywood-avenue-toronto-on?page=24&search_id=toronto-on&search_type=property_browse", "/properties/C4573099/401-270-rushton-road-toronto-on?page=24&search_id=toronto-on&search_type=property_browse", "/properties/C4573115/th-5-290-w-st-clair-avenue-toronto-on?page=24&search_id=toronto-on&search_type=property_browse", "/properties/C4573133/399-woburn-avenue-toronto-on?page=24&search_id=toronto-on&search_type=property_browse", "/properties/C4573063/2601-23-hollywood-avenue-toronto-on?page=24&search_id=toronto-on&search_type=property_browse"]},
{"price": ["\n$1,129,000\n", "\n$1,949,000\n", "\n$719,900\n", "\n$539,000\n", "\n$699,000\n", "\n$675,000\n", "\n$542,000\n", "\n$895,000\n", "\n$2,795,000\n", "\n$1,180,000\n", "\n$868,000\n", "\n$448,000\n", "\n$1,498,800\n", "\n$599,900\n", "\n$609,000\n", "\n$1,274,900\n", "\n$1,198,000\n", "\n$350,000\n", "\n$349,000\n", "\n$789,000\n", "\n$2,288,000\n", "\n$729,900\n"], "addr": ["57 Thirtieth Street, Toronto, ON, M8W 3B7", "5 Broadmead Avenue, Toronto, ON, M1M 1C3", "1229-500 Doris Avenue, Toronto, ON, M2N 0C1", "713-101 W Erskine Avenue, Toronto, ON, M4P 1Y5", "910-330 E Adelaide Street, Toronto, ON, M5A 4S9", "603-736 E Dundas Street, Toronto, ON, M5A 2C5", "1905-50 Lombard Street, Toronto, ON, M5C 2X4", "202-1 Glen Park Avenue, Toronto, ON, M6B 4M5", "413-38 Avenue Road, Toronto, ON, M5R 2G2", "183 Honiton Street, Toronto, ON, M3H 5N3", "1029-629 King Street, Toronto, ON, M5V 1M5", "605-78 Warren Road, Toronto, ON, M4V 2R6", "1215-230 W Queens Quay, Toronto, ON, M5J 2Y7", "201-205 Manning Avenue, Toronto, ON, M6J 2K7", "3102-361 W Front Street, Toronto, ON, M5V 3R5", "115-1 Ripley Avenue, Toronto, ON, M6S 4Z6", "10 Sturton Road, Toronto, ON, M9P 2C6", "1002-370 Dixon Road, Toronto, ON, M9R 1T2", "312-370 Dixon Road, Toronto, ON, M9R 1T2", "516-88 Park Lawn Road, Toronto, ON, M8Y 0B5", "16 Totteridge Road, Toronto, ON, M9A 1Z1", "422-8 Drummond Street, Toronto, ON, M8V 1Y8"], "link": ["/properties/W4565193/57-thirtieth-street-toronto-on?page=14&search_id=toronto-on&search_type=property_browse", "/properties/E4554867/5-broadmead-avenue-toronto-on?page=14&search_id=toronto-on&search_type=property_browse", "/properties/C4574877/1229-500-doris-avenue-toronto-on?page=14&search_id=toronto-on&search_type=property_browse", "/properties/C4575072/713-101-w-erskine-avenue-toronto-on?page=14&search_id=toronto-on&search_type=property_browse", "/properties/C4574670/910-330-e-adelaide-street-toronto-on?page=14&search_id=toronto-on&search_type=property_browse", "/properties/C4574587/603-736-e-dundas-street-toronto-on?page=14&search_id=toronto-on&search_type=property_browse", "/properties/C4574710/1905-50-lombard-street-toronto-on?page=14&search_id=toronto-on&search_type=property_browse", "/properties/C4574469/202-1-glen-park-avenue-toronto-on?page=14&search_id=toronto-on&search_type=property_browse", "/properties/C4574855/413-38-avenue-road-toronto-on?page=14&search_id=toronto-on&search_type=property_browse", "/properties/C4575049/183-honiton-street-toronto-on?page=14&search_id=toronto-on&search_type=property_browse", "/properties/C4574972/1029-629-king-street-toronto-on?page=14&search_id=toronto-on&search_type=property_browse", "/properties/C4574980/605-78-warren-road-toronto-on?page=14&search_id=toronto-on&search_type=property_browse", "/properties/C4574792/1215-230-w-queens-quay-toronto-on?page=14&search_id=toronto-on&search_type=property_browse", "/properties/C4574461/201-205-manning-avenue-toronto-on?page=14&search_id=toronto-on&search_type=property_browse", "/properties/C4574517/3102-361-w-front-street-toronto-on?page=14&search_id=toronto-on&search_type=property_browse", "/properties/W4574319/115-1-ripley-avenue-toronto-on?page=14&search_id=toronto-on&search_type=property_browse", "/properties/W4575004/10-sturton-road-toronto-on?page=14&search_id=toronto-on&search_type=property_browse", "/properties/W4574746/1002-370-dixon-road-toronto-on?page=14&search_id=toronto-on&search_type=property_browse", "/properties/W4575058/312-370-dixon-road-toronto-on?page=14&search_id=toronto-on&search_type=property_browse", "/properties/W4574586/516-88-park-lawn-road-toronto-on?page=14&search_id=toronto-on&search_type=property_browse", "/properties/W4574988/16-totteridge-road-toronto-on?page=14&search_id=toronto-on&search_type=property_browse", "/properties/W4574691/422-8-drummond-street-toronto-on?page=14&search_id=toronto-on&search_type=property_browse"]},
{"price": ["\n$829,900\n", "\n$1,949,000\n", "\n$529,900\n", "\n$490,000\n", "\n$1,699,000\n", "\n$674,900\n", "\n$1,149,000\n", "\n$3,688,888\n", "\n$669,000\n", "\n$898,800\n", "\n$1,698,000\n", "\n$989,000\n", "\n$969,800\n", "\n$515,990\n", "\n$420,000\n", "\n$539,900\n", "\n$689,000\n", "\n$679,900\n", "\n$1,299,000\n", "\n$1,089,000\n", "\n$479,000\n", "\n$899,888\n"], "addr": ["28 Medley Crescent, Toronto, ON, M1J 1Y3", "5 Broadmead Avenue, Toronto, ON, M1M 1C3", "411-50 Forest Manor Road, Toronto, ON, M2J 0E3", "329-27 Rean Drive, Toronto, ON, M2K 0A6", "60 Rainsford Road, Toronto, ON, M4L 3N6", "510-75 York Mills Road, Toronto, ON, M2P 2E7", "277 E Eglinton Avenue, Toronto, ON, M4P 1L3", "87 Harrison Road, Toronto, ON, M2L 1V9", "302-777 W Steeles Avenue, Toronto, ON, M2R 3Y4", "132B W Finch Avenue, Toronto, ON, M2N 2H9", "160 Johnston Avenue, Toronto, ON, M2N 1H3", "3107-750 Bay Street, Toronto, ON, M5G 1N6", "Ph506-915 W King Street, Toronto, ON, M6K 3M2", "1106-6 Eva Road, Toronto, ON, M9C 4Z5", "413-1040 The Queensway Avenue, Toronto, ON, M8Z 0A7", "408-2121 W Lake Shore Boulevard, Toronto, ON, M8V 1A1", "311-240 Scarlett Road, Toronto, ON, M6N 4X4", "306-1100 Briar Hill Avenue, Toronto, ON, M6B 0A9", "111 Humbercrest Boulevard, Toronto, ON, M6S 4L4", "216-1100 Kingston Road, Toronto, ON, M1N 1N4", "1408-55 Huntingdale Boulevard, Toronto, ON, M1W 2N9", "607-880 Grandview Way, Toronto, ON, M2N 7B2"], "link": ["/properties/E4546454/28-medley-crescent-toronto-on?page=13&search_id=toronto-on&search_type=property_browse", "/properties/E4554867/5-broadmead-avenue-toronto-on?page=13&search_id=toronto-on&search_type=property_browse", "/properties/C4575155/411-50-forest-manor-road-toronto-on?page=13&search_id=toronto-on&search_type=property_browse", "/properties/C4575295/329-27-rean-drive-toronto-on?page=13&search_id=toronto-on&search_type=property_browse", "/properties/E4574659/60-rainsford-road-toronto-on?page=13&search_id=toronto-on&search_type=property_browse", "/properties/C4575119/510-75-york-mills-road-toronto-on?page=13&search_id=toronto-on&search_type=property_browse", "/properties/C4575280/277-e-eglinton-avenue-toronto-on?page=13&search_id=toronto-on&search_type=property_browse", "/properties/C4575248/87-harrison-road-toronto-on?page=13&search_id=toronto-on&search_type=property_browse", "/properties/C4575269/302-777-w-steeles-avenue-toronto-on?page=13&search_id=toronto-on&search_type=property_browse", "/properties/C4575192/132b-w-finch-avenue-toronto-on?page=13&search_id=toronto-on&search_type=property_browse", "/properties/C4575078/160-johnston-avenue-toronto-on?page=13&search_id=toronto-on&search_type=property_browse", "/properties/C4575298/3107-750-bay-street-toronto-on?page=13&search_id=toronto-on&search_type=property_browse", "/properties/C4575077/ph506-915-w-king-street-toronto-on?page=13&search_id=toronto-on&search_type=property_browse", "/properties/W4575064/1106-6-eva-road-toronto-on?page=13&search_id=toronto-on&search_type=property_browse", "/properties/W4574480/1040-the-queensway-avenue-toronto-on?page=13&search_id=toronto-on&search_type=property_browse", "/properties/W4574837/408-2121-w-lake-shore-boulevard-toronto-on?page=13&search_id=toronto-on&search_type=property_browse", "/properties/W4574738/311-240-scarlett-road-toronto-on?page=13&search_id=toronto-on&search_type=property_browse", "/properties/W4574571/306-1100-briar-hill-avenue-toronto-on?page=13&search_id=toronto-on&search_type=property_browse", "/properties/W4574900/111-humbercrest-boulevard-toronto-on?page=13&search_id=toronto-on&search_type=property_browse", "/properties/E4574563/216-1100-kingston-road-toronto-on?page=13&search_id=toronto-on&search_type=property_browse", "/properties/E4575070/1408-55-huntingdale-boulevard-toronto-on?page=13&search_id=toronto-on&search_type=property_browse", "/properties/C4574462/607-880-grandview-way-toronto-on?page=13&search_id=toronto-on&search_type=property_browse"]},
{"price": ["\n$829,900\n", "\n$1,949,000\n", "\n$985,000\n", "\n$1,849,000\n", "\n$2,499,000\n", "\n$1,499,000\n", "\n$1,398,000\n", "\n$659,000\n", "\n$2,333,888\n", "\n$980,000\n", "\n$950,000\n", "\n$899,000\n", "\n$425,000\n", "\n$899,999\n", "\n$799,000\n", "\n$699,900\n", "\n$939,000\n", "\n$1,990,000\n", "\n$1,249,000\n", "\n$779,000\n", "\n$1,198,000\n", "\n$1,690,000\n"], "addr": ["28 Medley Crescent, Toronto, ON, M1J 1Y3", "5 Broadmead Avenue, Toronto, ON, M1M 1C3", "1807-170 Avenue Road, Toronto, ON, M5R 0A4", "70 Bude Street, Toronto, ON, M6C 1X8", "23 Gore Vale Avenue, Toronto, ON, M6J 2R5", "603 Cummer Avenue, Toronto, ON, M2K 2M5", "393 Old Orchard Grve, Toronto, ON, M5M 2G1", "401-22 Shallmar Boulevard, Toronto, ON, M5N 2Z8", "6 Parkland Road, Toronto, ON, M1N 1Y5", "Th19-7 Oakburn Crescent, Toronto, ON, M2N 2T5", "918 W Greenwood Avenue, Toronto, ON, M4J 4C1", "23 Wrenson Road, Toronto, ON, M4L 2G5", "2070-65 George Appleton Way, Toronto, ON, M3M 0A2", "1 Stanwood Crescent, Toronto, ON, M9M 1Z8", "25 Fort Dearborn Drive, Toronto, ON, M1V 3A6", "205-10 Wellesley Place, Toronto, ON, M4Y 1B1", "179 Rushton Road, Toronto, ON, M6G 3J2", "10 Cole Millway, Toronto, ON, M4N 3P8", "43 Lorraine Gardens, Toronto, ON, M9B 4Z7", "25 Eriksdale Road, Toronto, ON, M9C 2B8", "18 Adelpha Drive, Toronto, ON, M8Z 3A2", "127 Lake Crescent, Toronto, ON, M8V 1W2"], "link": ["/properties/E4546454/28-medley-crescent-toronto-on?page=17&search_id=toronto-on&search_type=property_browse", "/properties/E4554867/5-broadmead-avenue-toronto-on?page=17&search_id=toronto-on&search_type=property_browse", "/properties/C4574605/1807-170-avenue-road-toronto-on?page=17&search_id=toronto-on&search_type=property_browse", "/properties/C4574888/70-bude-street-toronto-on?page=17&search_id=toronto-on&search_type=property_browse", "/properties/C4574258/23-gore-vale-avenue-toronto-on?page=17&search_id=toronto-on&search_type=property_browse", "/properties/C4574424/603-cummer-avenue-toronto-on?page=17&search_id=toronto-on&search_type=property_browse", "/properties/C4574420/393-old-orchard-grve-toronto-on?page=17&search_id=toronto-on&search_type=property_browse", "/properties/C4574417/401-22-shallmar-boulevard-toronto-on?page=17&search_id=toronto-on&search_type=property_browse", "/properties/E4574387/6-parkland-road-toronto-on?page=17&search_id=toronto-on&search_type=property_browse", "/properties/C4574380/th19-7-oakburn-crescent-toronto-on?page=17&search_id=toronto-on&search_type=property_browse", "/properties/E4574399/918-w-greenwood-avenue-toronto-on?page=17&search_id=toronto-on&search_type=property_browse", "/properties/E4574401/23-wrenson-road-toronto-on?page=17&search_id=toronto-on&search_type=property_browse", "/properties/W4574362/2070-65-e-george-appleton-way-toronto-on?page=17&search_id=toronto-on&search_type=property_browse", "/properties/W4574352/1-stanwood-crescent-toronto-on?page=17&search_id=toronto-on&search_type=property_browse", "/properties/E4574351/25-fort-dearborn-drive-toronto-on?page=17&search_id=toronto-on&search_type=property_browse", "/properties/C4574361/205-10-wellesley-place-toronto-on?page=17&search_id=toronto-on&search_type=property_browse", "/properties/C4574329/179-rushton-road-toronto-on?page=17&search_id=toronto-on&search_type=property_browse", "/properties/C4574312/10-cole-millway-toronto-on?page=17&search_id=toronto-on&search_type=property_browse", "/properties/W4574277/43-lorraine-gardens-toronto-on?page=17&search_id=toronto-on&search_type=property_browse", "/properties/W4574163/25-eriksdale-road-toronto-on?page=17&search_id=toronto-on&search_type=property_browse", "/properties/W4574200/18-adelpha-drive-toronto-on?page=17&search_id=toronto-on&search_type=property_browse", "/properties/W4574188/127-lake-crescent-toronto-on?page=17&search_id=toronto-on&search_type=property_browse"]},
{"price": ["\n$1,999,999\n", "\n$1,129,000\n", "\n$799,000\n", "\n$269,900\n", "\n$799,000\n", "\n$1,395,000\n", "\n$949,000\n", "\n$672,000\n", "\n$629,900\n", "\n$1,299,000\n", "\n$969,000\n", "\n$899,999\n", "\n$789,000\n", "\n$767,000\n", "\n$669,000\n", "\n$2,359,000\n", "\n$699,900\n", "\n$969,000\n", "\n$1,449,000\n", "\n$599,000\n", "\n$999,000\n", "\n$799,800\n"], "addr": ["67 Sylvan Avenue, Toronto, ON, M1M 1J9", "57 Thirtieth Street, Toronto, ON, M8W 3B7", "6006-30 Shore Breeze Drive, Toronto, ON, M8V 0J1", "407-80 Grandravine Drive, Toronto, ON, M3J 1B2", "19-115 Long Branch Avenue, Toronto, ON, M8W 0A9", "220-80 Marine Parade Drive, Toronto, ON, M8V 4B4", "29 Chryessa Avenue, Toronto, ON, M6N 4T4", "1011-250 Scarlett Road, Toronto, ON, M6N 4X5", "387 Old Weston Road, Toronto, ON, M6N 3A9", "62 Raymond Avenue, Toronto, ON, M6S 2B4", "105 Viella Street, Toronto, ON, M6N 5C7", "21 Dunelm Street, Toronto, ON, M1J 3G2", "221-347 Sorauren Avenue, Toronto, ON, M6R 2G5", "917-35 Ormskirk Avenue, Toronto, ON, M6S 1A8", "79 Hawkshead Crescent, Toronto, ON, M1W 2Z4", "107 Sylvan Avenue, Toronto, ON, M1M 1J9", "15 Presley Avenue, Toronto, ON, M1L 3P4", "18 King Edward Avenue, Toronto, ON, M4C 5J6", "40 Westlake Crescent, Toronto, ON, M4C 2X2", "195 Westlake Avenue, Toronto, ON, M4C 4S6", "52 Barrington Avenue, Toronto, ON, M4C 4Y7", "9 Adair Road, Toronto, ON, M4B 1V4"], "link": ["/properties/E4513401/67-sylvan-avenue-toronto-on?page=15&search_id=toronto-on&search_type=property_browse", "/properties/W4565193/57-thirtieth-street-toronto-on?page=15&search_id=toronto-on&search_type=property_browse", "/properties/W4574823/6006-30-shore-breeze-drive-toronto-on?page=15&search_id=toronto-on&search_type=property_browse", "/properties/W4574600/407-80-grandravine-drive-toronto-on?page=15&search_id=toronto-on&search_type=property_browse", "/properties/W4574977/19-115-long-branch-avenue-toronto-on?page=15&search_id=toronto-on&search_type=property_browse", "/properties/W4574774/220-80-marine-parade-drive-toronto-on?page=15&search_id=toronto-on&search_type=property_browse", "/properties/W4574696/29-chryessa-avenue-toronto-on?page=15&search_id=toronto-on&search_type=property_browse", "/properties/W4574612/1011-250-scarlett-road-toronto-on?page=15&search_id=toronto-on&search_type=property_browse", "/properties/W4574673/387-old-weston-road-toronto-on?page=15&search_id=toronto-on&search_type=property_browse", "/properties/W4574524/62-raymond-avenue-toronto-on?page=15&search_id=toronto-on&search_type=property_browse", "/properties/W4574572/105-viella-street-toronto-on?page=15&search_id=toronto-on&search_type=property_browse", "/properties/E4574736/21-dunelm-street-toronto-on?page=15&search_id=toronto-on&search_type=property_browse", "/properties/W4574730/221-347-sorauren-avenue-toronto-on?page=15&search_id=toronto-on&search_type=property_browse", "/properties/W4575016/917-35-ormskirk-avenue-toronto-on?page=15&search_id=toronto-on&search_type=property_browse", "/properties/E4574967/79-hawkshead-crescent-toronto-on?page=15&search_id=toronto-on&search_type=property_browse", "/properties/E4574750/107-sylvan-avenue-toronto-on?page=15&search_id=toronto-on&search_type=property_browse", "/properties/E4574658/15-presley-avenue-toronto-on?page=15&search_id=toronto-on&search_type=property_browse", "/properties/E4574676/18-king-edward-avenue-toronto-on?page=15&search_id=toronto-on&search_type=property_browse", "/properties/E4574638/40-westlake-crescent-toronto-on?page=15&search_id=toronto-on&search_type=property_browse", "/properties/E4574783/195-westlake-avenue-toronto-on?page=15&search_id=toronto-on&search_type=property_browse", "/properties/E4574913/52-barrington-avenue-toronto-on?page=15&search_id=toronto-on&search_type=property_browse", "/properties/E4574979/9-adair-road-toronto-on?page=15&search_id=toronto-on&search_type=property_browse"]},
{"price": ["\n$1,999,999\n", "\n$1,129,000\n", "\n$604,900\n", "\n$778,888\n", "\n$658,900\n", "\n$2,050,000\n", "\n$1,149,800\n", "\n$1,059,000\n", "\n$668,000\n", "\n$3,198,000\n", "\n$1,589,000\n", "\n$409,900\n", "\n$959,900\n", "\n$599,999\n", "\n$898,888\n", "\n$2,195,000\n", "\n$1,135,000\n", "\n$619,900\n", "\n$899,000\n", "\n$799,000\n", "\n$899,900\n", "\n$2,000,000\n"], "addr": ["67 Sylvan Avenue, Toronto, ON, M1M 1J9", "57 Thirtieth Street, Toronto, ON, M8W 3B7", "72-655D Warden Avenue, Toronto, ON, M1L 3Z5", "5102-1 E Bloor Street, Toronto, ON, M4W 1A9", "2030-460 E Adelaide Street, Toronto, ON, M5A 1N6", "108-349 W St Clair Avenue, Toronto, ON, M5P 1N3", "389 Winnett Avenue, Toronto, ON, M6C 3M2", "18 Falwyn Avenue, Toronto, ON, M6C 1K6", "2107-15 Iceboat Terrace, Toronto, ON, M5V 4A5", "6 Ashwood Crescent, Toronto, ON, M9A 1Z3", "5 Trudy Road, Toronto, ON, M2J 2Y7", "101-11 Neilson Drive, Toronto, ON, M9C 1V4", "7 Thornly Crescent, Toronto, ON, M9B 2M4", "8 Edgeware Drive, Toronto, ON, M8W 1T4", "5-38 Mendota Road, Toronto, ON, M8Y 1G2", "85 Burrows Avenue, Toronto, ON, M9B 4X2", "184 Gamma Street, Toronto, ON, M8W 4G4", "509-240 Scarlett Road, Toronto, ON, M6N 4X4", "1 Ray Avenue, Toronto, ON, M6M 2A7", "28 Fishleigh Drive, Toronto, ON, M1N 1G9", "724-10 Guildwood Pkwy, Toronto, ON, M1E 5B5", "267 West Point Avenue, Toronto, ON, M1C 2R9"], "link": ["/properties/E4513401/67-sylvan-avenue-toronto-on?page=12&search_id=toronto-on&search_type=property_browse", "/properties/W4565193/57-thirtieth-street-toronto-on?page=12&search_id=toronto-on&search_type=property_browse", "/properties/E4575355/72-655d-warden-avenue-toronto-on?page=12&search_id=toronto-on&search_type=property_browse", "/properties/C4575322/5102-1-e-bloor-street-toronto-on?page=12&search_id=toronto-on&search_type=property_browse", "/properties/C4575447/2030-460-e-adelaide-street-toronto-on?page=12&search_id=toronto-on&search_type=property_browse", "/properties/C4575323/108-349-w-st-clair-avenue-toronto-on?page=12&search_id=toronto-on&search_type=property_browse", "/properties/C4575407/389-winnett-avenue-toronto-on?page=12&search_id=toronto-on&search_type=property_browse", "/properties/C4575332/18-falwyn-avenue-toronto-on?page=12&search_id=toronto-on&search_type=property_browse", "/properties/C4575435/2107-15-iceboat-terrace-toronto-on?page=12&search_id=toronto-on&search_type=property_browse", "/properties/W4575082/6-ashwood-crescent-toronto-on?page=12&search_id=toronto-on&search_type=property_browse", "/properties/C4575303/5-trudy-road-toronto-on?page=12&search_id=toronto-on&search_type=property_browse", "/properties/W4575071/101-11-neilson-drive-toronto-on?page=12&search_id=toronto-on&search_type=property_browse", "/properties/W4575143/7-thornly-crescent-toronto-on?page=12&search_id=toronto-on&search_type=property_browse", "/properties/W4575266/8-edgeware-drive-toronto-on?page=12&search_id=toronto-on&search_type=property_browse", "/properties/W4575293/3-38-mendota-road-toronto-on?page=12&search_id=toronto-on&search_type=property_browse", "/properties/W4575307/85-burrows-avenue-toronto-on?page=12&search_id=toronto-on&search_type=property_browse", "/properties/W4575111/184-gamma-street-toronto-on?page=12&search_id=toronto-on&search_type=property_browse", "/properties/W4575304/509-240-scarlett-road-toronto-on?page=12&search_id=toronto-on&search_type=property_browse", "/properties/W4575127/1-ray-avenue-toronto-on?page=12&search_id=toronto-on&search_type=property_browse", "/properties/E4575154/28-fishleigh-drive-toronto-on?page=12&search_id=toronto-on&search_type=property_browse", "/properties/E4575179/724-10-guildwood-pkwy-toronto-on?page=12&search_id=toronto-on&search_type=property_browse", "/properties/E4575121/267-west-point-avenue-toronto-on?page=12&search_id=toronto-on&search_type=property_browse"]},
{"price": ["\n$1,949,000\n", "\n$829,900\n", "\n$799,900\n", "\n$1,139,000\n", "\n$1,868,000\n", "\n$659,900\n", "\n$689,000\n", "\n$4,195,000\n", "\n$1,079,000\n", "\n$11,988,888\n", "\n$899,900\n", "\n$2,749,000\n", "\n$899,900\n", "\n$3,399,000\n", "\n$829,000\n", "\n$628,999\n", "\n$799,000\n", "\n$1,149,900\n", "\n$899,900\n", "\n$899,000\n", "\n$1,399,000\n", "\n$670,000\n"], "addr": ["5 Broadmead Avenue, Toronto, ON, M1M 1C3", "28 Medley Crescent, Toronto, ON, M1J 1Y3", "242 Aylesworth Avenue, Toronto, ON, M1N 2J6", "91 Whitburn Crescent, Toronto, ON, M3M 2S5", "62 Glenlake Avenue, Toronto, ON, M6P 1C9", "2 Glasgow Avenue, Toronto, ON, M1K 1C1", "2-1 Bastedo Avenue, Toronto, ON, M4C 5S7", "8 Frivick Court, Toronto, ON, M2M 3P6", "83 Glenmount Park Road, Toronto, ON, M4E 2N1", "Toronto, ON", "201-39 Sherbourne Street, Toronto, ON, M5A 1K2", "31 Glen Echo Road, Toronto, ON, M4N 2E2", "618-40 Sylvan Valley Way, Toronto, ON, M5M 4M3", "404 Brunswick Avenue, Toronto, ON, M5R 2Z4", "1512-35 Bastion Street, Toronto, ON, M5V 0C2", "1709-381 W Front Street, Toronto, ON, M5V 3R8", "126 Van Horne Avenue, Toronto, ON, M2J 2T1", "110 Sixteenth Street, Toronto, ON, M8V 3K1", "23 Snowy Owl Way, Toronto, ON, M1X 0B4", "2207-2045 Lake Shore Boulevard, Toronto, ON, M8V 2Z6", "14 Runnymede Road, Toronto, ON, M6S 2Y2", "505-89 Dunfield Avenue, Toronto, ON, M4S 0A4"], "link": ["/properties/E4554867/5-broadmead-avenue-toronto-on?page=11&search_id=toronto-on&search_type=property_browse", "/properties/E4546454/28-medley-crescent-toronto-on?page=11&search_id=toronto-on&search_type=property_browse", "/properties/E4575650/242-aylesworth-avenue-toronto-on?page=11&search_id=toronto-on&search_type=property_browse", "/properties/W4575587/91-whitburn-crescent-toronto-on?page=11&search_id=toronto-on&search_type=property_browse", "/properties/W4575546/62-glenlake-avenue-toronto-on?page=11&search_id=toronto-on&search_type=property_browse", "/properties/E4575647/2-glasgow-avenue-toronto-on?page=11&search_id=toronto-on&search_type=property_browse", "/properties/E4575589/2-1-bastedo-avenue-toronto-on?page=11&search_id=toronto-on&search_type=property_browse", "/properties/C4575578/8-frivick-court-toronto-on?page=11&search_id=toronto-on&search_type=property_browse", "/properties/E4575616/83-glenmount-park-road-toronto-on?page=11&search_id=toronto-on&search_type=property_browse", "/properties/C4575565/toronto-on?page=11&search_id=toronto-on&search_type=property_browse", "/properties/C4575526/201-39-sherbourne-street-toronto-on?page=11&search_id=toronto-on&search_type=property_browse", "/properties/C4575510/31-glen-echo-road-toronto-on?page=11&search_id=toronto-on&search_type=property_browse", "/properties/C4575577/618-40-sylvan-valley-way-toronto-on?page=11&search_id=toronto-on&search_type=property_browse", "/properties/C4575480/404-brunswick-avenue-toronto-on?page=11&search_id=toronto-on&search_type=property_browse", "/properties/C4575528/1512-35-bastion-street-toronto-on?page=11&search_id=toronto-on&search_type=property_browse", "/properties/C4575671/1709-381-w-front-street-toronto-on?page=11&search_id=toronto-on&search_type=property_browse", "/properties/C4574377/126-van-horne-avenue-toronto-on?page=11&search_id=toronto-on&search_type=property_browse", "/properties/W4575441/110-sixteenth-street-toronto-on?page=11&search_id=toronto-on&search_type=property_browse", "/properties/E4575353/23-snowy-owl-way-toronto-on?page=11&search_id=toronto-on&search_type=property_browse", "/properties/W4575342/2207-2045-lake-shore-boulevard-toronto-on?page=11&search_id=toronto-on&search_type=property_browse", "/properties/W4575341/14-runnymede-road-toronto-on?page=11&search_id=toronto-on&search_type=property_browse", "/properties/C4575429/505-89-dunfield-avenue-toronto-on?page=11&search_id=toronto-on&search_type=property_browse"]},
{"price": ["\n$829,900\n", "\n$1,999,999\n", "\n$1,399,000\n", "\n$384,900\n", "\n$1,085,000\n", "\n$578,000\n", "\n$609,000\n", "\n$1,198,000\n", "\n$3,795,000\n", "\n$948,000\n", "\n$429,000\n", "\n$899,900\n", "\n$869,000\n", "\n$718,900\n", "\n$615,000\n", "\n$839,000\n", "\n$1,585,000\n", "\n$789,000\n", "\n$1,699,000\n", "\n$869,900\n", "\n$649,900\n", "\n$1,298,000\n"], "addr": ["28 Medley Crescent, Toronto, ON, M1J 1Y3", "67 Sylvan Avenue, Toronto, ON, M1M 1J9", "440 N Westmoreland Street, Toronto, ON, M6H 3A7", "Toronto, ON", "47 Bloorlea Crescent, Toronto, ON, M9B 1P2", "203-5 Richgrove Drive, Toronto, ON, M9R 0A3", "1113-155 N Legion Road, Toronto, ON, M8Y 0A7", "61 Hillsview Avenue, Toronto, ON, M6P 1J4", "67 The Kingsway, Toronto, ON, M8X 2T3", "708-20 Gothic Avenue, Toronto, ON, M6P 1T5", "2009-5 Valhalla Inn Road, Toronto, ON, M9B 0B1", "96 East Drive, Toronto, ON, M6N 2N9", "161 North Carson Street, Toronto, ON, M8W 4E1", "99 Mare Crescent, Toronto, ON, M9W 7E5", "#3409-56 Annie Craig Drive, Toronto, ON, M8V 0C8", "1507-2045 W Lake Shore Boulevard, Toronto, ON, M8V 2Z6", "156 Humbercrest Boulevard, Toronto, ON, M6S 4L3", "11 Duern Street, Toronto, ON, M6N 4G6", "560 Nairn Avenue, Toronto, ON, M6E 4J6", "114-80 Quebec Avenue, Toronto, ON, M6P 4B7", "48 Ianhall Road, Toronto, ON, M3M 2B1", "239 Old Kingston Road, Toronto, ON, M1C 1B3"], "link": ["/properties/E4546454/28-medley-crescent-toronto-on?page=22&search_id=toronto-on&search_type=property_browse", "/properties/E4513401/67-sylvan-avenue-toronto-on?page=22&search_id=toronto-on&search_type=property_browse", "/properties/W4573452/440-n-westmoreland-street-toronto-on?page=22&search_id=toronto-on&search_type=property_browse", "/properties/W4573423/toronto-on?page=22&search_id=toronto-on&search_type=property_browse", "/properties/W4573421/47-bloorlea-crescent-toronto-on?page=22&search_id=toronto-on&search_type=property_browse", "/properties/W4573304/203-5-richgrove-drive-toronto-on?page=22&search_id=toronto-on&search_type=property_browse", "/properties/W4573314/1113-155-n-legion-road-toronto-on?page=22&search_id=toronto-on&search_type=property_browse", "/properties/W4573262/61-hillsview-avenue-toronto-on?page=22&search_id=toronto-on&search_type=property_browse", "/properties/W4573280/67-the-kingsway-toronto-on?page=22&search_id=toronto-on&search_type=property_browse", "/properties/W4573269/708-20-gothic-avenue-toronto-on?page=22&search_id=toronto-on&search_type=property_browse", "/properties/W4573258/2009-5-valhalla-inn-road-toronto-on?page=22&search_id=toronto-on&search_type=property_browse", "/properties/W4573222/96-east-drive-toronto-on?page=22&search_id=toronto-on&search_type=property_browse", "/properties/W4573189/161-north-carson-street-toronto-on?page=22&search_id=toronto-on&search_type=property_browse", "/properties/W4573219/99-mare-crescent-toronto-on?page=22&search_id=toronto-on&search_type=property_browse", "/properties/W4573181/3409-56-annie-craig-drive-toronto-on?page=22&search_id=toronto-on&search_type=property_browse", "/properties/W4573159/1507-2045-w-lake-shore-boulevard-toronto-on?page=22&search_id=toronto-on&search_type=property_browse", "/properties/W4573173/156-humbercrest-boulevard-toronto-on?page=22&search_id=toronto-on&search_type=property_browse", "/properties/W4573150/11-duern-street-toronto-on?page=22&search_id=toronto-on&search_type=property_browse", "/properties/W4573152/560-nairn-avenue-toronto-on?page=22&search_id=toronto-on&search_type=property_browse", "/properties/W4573074/114-80-quebec-avenue-toronto-on?page=22&search_id=toronto-on&search_type=property_browse", "/properties/W4573037/48-ianhall-road-toronto-on?page=22&search_id=toronto-on&search_type=property_browse", "/properties/E4573411/239-old-kingston-road-toronto-on?page=22&search_id=toronto-on&search_type=property_browse"]},
{"price": ["\n$1,129,000\n", "\n$1,999,999\n", "\n$850,000\n", "\n$848,000\n", "\n$799,888\n", "\n$2,998,888\n", "\n$2,799,888\n", "\n$849,000\n", "\n$1,658,800\n", "\n$450,000\n", "\n$629,000\n", "\n$769,900\n", "\n$489,000\n", "\n$365,000\n", "\n$699,000\n", "\n$539,000\n", "\n$1,799,000\n", "\n$680,000\n", "\n$2,049,000\n", "\n$539,000\n", "\n$549,900\n", "\n$1,075,000\n"], "addr": ["57 Thirtieth Street, Toronto, ON, M8W 3B7", "67 Sylvan Avenue, Toronto, ON, M1M 1J9", "3706-38 Grenville Street, Toronto, ON, M4Y 1A5", "1006-44 W Gerrard Street, Toronto, ON, M5G 2K2", "11 Bondhead Place, Toronto, ON, M9V 2L9", "14 Ballantyne Court, Toronto, ON, M9A 1W9", "48 Forest Grove Drive, Toronto, ON, M2K 1Z3", "24 Glenburn Avenue, Toronto, ON, M4B 2X2", "1715 Pharmacy Avenue, Toronto, ON, M1T 1H1", "407-90 Dale Avenue, Toronto, ON, M1J 3N4", "814-1091 Kingston Road, Toronto, ON, M1N 4E5", "131 Taysham Crescent, Toronto, ON, M9V 1X4", "8-68 Winston Park Boulevard, Toronto, ON, M3K 1C2", "303-40 Panorama Court, Toronto, ON, M9V 4M1", "1609-2269 W Lake Shore Boulevard, Toronto, ON, M8V 3X6", "2006-155 Marlee Avenue, Toronto, ON, M6B 4B5", "305-11 William Carson Crescent, Toronto, ON, M2P 2G1", "2407-70 Temperance Street, Toronto, ON, M5H 4E8", "114 Wimbleton Road, Toronto, ON, M9A 3S6", "3408-36 Park Lawn Road, Toronto, ON, M8Y 3H8", "1004-33 Shore Breeze Drive, Toronto, ON, M8V 1A1", "8 West Deane Park Drive, Toronto, ON, M9B 2R4"], "link": ["/properties/W4565193/57-thirtieth-street-toronto-on?page=10&search_id=toronto-on&search_type=property_browse", "/properties/E4513401/67-sylvan-avenue-toronto-on?page=10&search_id=toronto-on&search_type=property_browse", "/properties/C4576546/3706-38-grenville-street-toronto-on?page=10&search_id=toronto-on&search_type=property_browse", "/properties/C4577228/1006-44-w-gerrard-street-toronto-on?page=10&search_id=toronto-on&search_type=property_browse", "/properties/W4576040/11-bondhead-place-toronto-on?page=10&search_id=toronto-on&search_type=property_browse", "/properties/W4576233/14-ballantyne-court-toronto-on?page=10&search_id=toronto-on&search_type=property_browse", "/properties/C4577322/48-forest-grove-drive-toronto-on?page=10&search_id=toronto-on&search_type=property_browse", "/properties/E4576919/24-glenburn-avenue-toronto-on?page=10&search_id=toronto-on&search_type=property_browse", "/properties/E4577382/1715-pharmacy-avenue-toronto-on?page=10&search_id=toronto-on&search_type=property_browse", "/properties/E4575699/407-90-dale-avenue-toronto-on?page=10&search_id=toronto-on&search_type=property_browse", "/properties/E4574453/814-1091-kingston-road-toronto-on?page=10&search_id=toronto-on&search_type=property_browse", "/properties/W4574024/toronto-on?page=10&search_id=toronto-on&search_type=property_browse", "/properties/W4573730/8-68-winston-park-boulevard-toronto-on?page=10&search_id=toronto-on&search_type=property_browse", "/properties/W4575704/303-40-panorama-court-toronto-on?page=10&search_id=toronto-on&search_type=property_browse", "/properties/W4575715/1609-2269-w-lake-shore-boulevard-toronto-on?page=10&search_id=toronto-on&search_type=property_browse", "/properties/W4575709/2006-155-marlee-avenue-toronto-on?page=10&search_id=toronto-on&search_type=property_browse", "/properties/C4575725/11-william-carson-crescent-toronto-on?page=10&search_id=toronto-on&search_type=property_browse", "/properties/C4573339/2407-70-temperance-street-toronto-on?page=10&search_id=toronto-on&search_type=property_browse", "/properties/W4575523/114-wimbleton-road-toronto-on?page=10&search_id=toronto-on&search_type=property_browse", "/properties/W4575611/3408-36-park-lawn-road-toronto-on?page=10&search_id=toronto-on&search_type=property_browse", "/properties/W4575569/1004-33-shore-breeze-drive-toronto-on?page=10&search_id=toronto-on&search_type=property_browse", "/properties/W4575473/8-west-deane-park-drive-toronto-on?page=10&search_id=toronto-on&search_type=property_browse"]},
{"price": ["\n$1,999,999\n", "\n$829,900\n", "\n$3,850,000\n", "\n$829,000\n", "\n$1,820,000\n", "\n$3,100,000\n", "\n$880,000\n", "\n$589,000\n", "\n$675,000\n", "\n$799,000\n", "\n$1,350,000\n", "\n$899,000\n", "\n$399,999\n", "\n$699,000\n", "\n$950,000\n", "\n$399,000\n", "\n$815,000\n", "\n$820,000\n", "\n$680,000\n", "\n$629,000\n", "\n$765,900\n", "\n$659,900\n"], "addr": ["67 Sylvan Avenue, Toronto, ON, M1M 1J9", "28 Medley Crescent, Toronto, ON, M1J 1Y3", "394 Walmer Road, Toronto, ON, M5R 2Y4", "306-33 Delisle Avenue, Toronto, ON, M4V 3C7", "306-380 Macpherson Avenue, Toronto, ON, M4V 3E3", "501-88 Davenport Road, Toronto, ON, M5R 0A5", "6507-88 E Harbour Street, Toronto, ON, M5J 0C3", "1905-12 York Street, Toronto, ON, M5J 2Z2", "4802-35 Mariner Terrace, Toronto, ON, M5V 3V9", "26 Henderson Avenue, Toronto, ON, M6J 2B8", "419 Crawford Street, Toronto, ON, M6G 3J7", "311-761 Bay Street, Toronto, ON, M5G 2R2", "719W-36 Lisgar Street, Toronto, ON, M6J 3G2", "2006-44 St Joseph Street, Toronto, ON, M4Y 2W4", "41 Brookfield Street, Toronto, ON, M6J 3A8", "307-705 W King Street, Toronto, ON, M5V 2W8", "2011-218 W Queens Quay, Toronto, ON, M5J 2Y6", "1208-355 W King Street, Toronto, ON, M5V 1J6", "607-736 Spadina Avenue, Toronto, ON, M5S 2J6", "1209-801 Bay Street, Toronto, ON, M5S 1Y9", "2809-1080 Bay Street, Toronto, ON, M5S 0A5", "925-50 Western Battery Road, Toronto, ON, M6K 3P1"], "link": ["/properties/E4513401/67-sylvan-avenue-toronto-on?page=9&search_id=toronto-on&search_type=property_browse", "/properties/E4546454/28-medley-crescent-toronto-on?page=9&search_id=toronto-on&search_type=property_browse", "/properties/C4576493/394-walmer-road-toronto-on?page=9&search_id=toronto-on&search_type=property_browse", "/properties/C4575973/306-33-delisle-avenue-toronto-on?page=9&search_id=toronto-on&search_type=property_browse", "/properties/C4576763/306-380-macpherson-avenue-toronto-on?page=9&search_id=toronto-on&search_type=property_browse", "/properties/C4577438/501-88-davenport-road-toronto-on?page=9&search_id=toronto-on&search_type=property_browse", "/properties/C4577388/6507-88-e-harbour-street-toronto-on?page=9&search_id=toronto-on&search_type=property_browse", "/properties/C4577152/1905-12-york-street-toronto-on?page=9&search_id=toronto-on&search_type=property_browse", "/properties/C4576768/4802-35-mariner-terrace-toronto-on?page=9&search_id=toronto-on&search_type=property_browse", "/properties/C4576918/26-henderson-avenue-toronto-on?page=9&search_id=toronto-on&search_type=property_browse", "/properties/C4576680/419-crawford-street-toronto-on?page=9&search_id=toronto-on&search_type=property_browse", "/properties/C4576568/311-761-bay-street-toronto-on?page=9&search_id=toronto-on&search_type=property_browse", "/properties/C4577226/719w-36-lisgar-street-toronto-on?page=9&search_id=toronto-on&search_type=property_browse", "/properties/C4576476/2006-44-st-joseph-street-toronto-on?page=9&search_id=toronto-on&search_type=property_browse", "/properties/C4575854/41-brookfield-street-toronto-on?page=9&search_id=toronto-on&search_type=property_browse", "/properties/C4575875/307-705-w-king-street-toronto-on?page=9&search_id=toronto-on&search_type=property_browse", "/properties/C4576304/2011-218-w-queens-quay-toronto-on?page=9&search_id=toronto-on&search_type=property_browse", "/properties/C4576320/1208-355-w-king-street-toronto-on?page=9&search_id=toronto-on&search_type=property_browse", "/properties/C4576165/607-736-spadina-avenue-toronto-on?page=9&search_id=toronto-on&search_type=property_browse", "/properties/C4575819/1209-801-bay-street-toronto-on?page=9&search_id=toronto-on&search_type=property_browse", "/properties/C4575774/2809-1080-bay-street-toronto-on?page=9&search_id=toronto-on&search_type=property_browse", "/properties/C4577323/925-50-western-battery-road-toronto-on?page=9&search_id=toronto-on&search_type=property_browse"]},
{"price": ["\n$829,900\n", "\n$1,949,000\n", "\n$695,000\n", "\n$775,000\n", "\n$749,000\n", "\n$1,199,000\n", "\n$469,900\n", "\n$789,000\n", "\n$515,000\n", "\n$1,640,000\n", "\n$2,498,000\n", "\n$859,000\n", "\n$612,000\n", "\n$620,000\n", "\n$6,099,000\n", "\n$3,498,888\n", "\n$2,785,000\n", "\n$7,500,000\n", "\n$679,900\n", "\n$3,895,000\n", "\n$2,950,000\n", "\n$1,895,000\n"], "addr": ["28 Medley Crescent, Toronto, ON, M1J 1Y3", "5 Broadmead Avenue, Toronto, ON, M1M 1C3", "415-22 Leader Lane, Toronto, ON, M5E 0B2", "304-39 Sherbourne Street, Toronto, ON, M5A 0L8", "1406-110 E Charles Street, Toronto, ON, M4Y 1T5", "1307-1 E Bloor Street, Toronto, ON, M4W 1A9", "1505-133 Torresdale Avenue, Toronto, ON, M2R 3T2", "1808-10 Torresdale Avenue, Toronto, ON, M2R 3V8", "1506-509 Beecroft Road, Toronto, ON, M2N 0A3", "25 Yorkview Drive, Toronto, ON, M2N 2R9", "6 Community Circ, Toronto, ON, M2R 1W5", "117-455 Rosewell Avenue, Toronto, ON, M4R 2B6", "# 315-935 W Sheppard Avenue, Toronto, ON, M3H 2T7", "604-3018 Yonge Street, Toronto, ON, M4N 2K4", "167 Coldstream Avenue, Toronto, ON, M5N 1X7", "279 Cortleigh Boulevard, Toronto, ON, M5N 1R1", "509 Fairlawn Avenue, Toronto, ON, M5M 1V3", "378 Russell Hill Road, Toronto, ON, M4V 2V2", "30 Rockvale Avenue, Toronto, ON, M6E 3A9", "22 Lytton Boulevard, Toronto, ON, M4R 1L1", "2 Frank Crescent, Toronto, ON, M6G 3K5", "503-63 W St Clair Avenue, Toronto, ON, M4V 2Y9"], "link": ["/properties/E4546454/28-medley-crescent-toronto-on?page=8&search_id=toronto-on&search_type=property_browse", "/properties/E4554867/5-broadmead-avenue-toronto-on?page=8&search_id=toronto-on&search_type=property_browse", "/properties/C4577105/415-22-leader-lane-toronto-on?page=8&search_id=toronto-on&search_type=property_browse", "/properties/C4576653/304-39-sherbourne-street-toronto-on?page=8&search_id=toronto-on&search_type=property_browse", "/properties/C4576754/1406-110-e-charles-street-toronto-on?page=8&search_id=toronto-on&search_type=property_browse", "/properties/C4576099/1307-1-e-bloor-street-toronto-on?page=8&search_id=toronto-on&search_type=property_browse", "/properties/C4576152/1505-133-torresdale-avenue-toronto-on?page=8&search_id=toronto-on&search_type=property_browse", "/properties/C4576299/1808-10-torresdale-avenue-toronto-on?page=8&search_id=toronto-on&search_type=property_browse", "/properties/C4576149/1506-509-beecroft-road-toronto-on?page=8&search_id=toronto-on&search_type=property_browse", "/properties/C4577080/25-yorkview-drive-toronto-on?page=8&search_id=toronto-on&search_type=property_browse", "/properties/C4575916/6-community-circ-toronto-on?page=8&search_id=toronto-on&search_type=property_browse", "/properties/C4576790/117-455-rosewell-avenue-toronto-on?page=8&search_id=toronto-on&search_type=property_browse", "/properties/C4575767/315-935-w-sheppard-avenue-toronto-on?page=8&search_id=toronto-on&search_type=property_browse", "/properties/C4577469/604-3018-yonge-street-toronto-on?page=8&search_id=toronto-on&search_type=property_browse", "/properties/C4576169/167-coldstream-avenue-toronto-on?page=8&search_id=toronto-on&search_type=property_browse", "/properties/C4575814/279-cortleigh-boulevard-toronto-on?page=8&search_id=toronto-on&search_type=property_browse", "/properties/C4576248/509-fairlawn-avenue-toronto-on?page=8&search_id=toronto-on&search_type=property_browse", "/properties/C4577479/378-russell-hill-road-toronto-on?page=8&search_id=toronto-on&search_type=property_browse", "/properties/C4575803/30-rockvale-avenue-toronto-on?page=8&search_id=toronto-on&search_type=property_browse", "/properties/C4576297/22-lytton-boulevard-toronto-on?page=8&search_id=toronto-on&search_type=property_browse", "/properties/C4575970/2-frank-crescent-toronto-on?page=8&search_id=toronto-on&search_type=property_browse", "/properties/C4576515/503-63-w-st-clair-avenue-toronto-on?page=8&search_id=toronto-on&search_type=property_browse"]},
{"price": ["\n$1,999,999\n", "\n$1,129,000\n", "\n$1,763,000\n", "\n$1,568,000\n", "\n$3,188,000\n", "\n$1,318,000\n", "\n$920,000\n", "\n$519,000\n", "\n$3,699,990\n", "\n$535,000\n", "\n$779,900\n", "\n$2,348,800\n", "\n$729,000\n", "\n$749,900\n", "\n$438,000\n", "\n$698,800\n", "\n$2,975,000\n", "\n$2,599,000\n", "\n$895,000\n", "\n$4,495,000\n", "\n$799,900\n", "\n$549,000\n"], "addr": ["67 Sylvan Avenue, Toronto, ON, M1M 1J9", "57 Thirtieth Street, Toronto, ON, M8W 3B7", "29 Tobruk Crescent, Toronto, ON, M2M 3B3", "2121-80 Harrison Garden Boulevard, Toronto, ON, M2N 7E3", "382 Ruth Avenue, Toronto, ON, M2M 2J1", "15-3180 E Bayview Avenue, Toronto, ON, M2N 6W2", "8 Flaming Rose Way, Toronto, ON, M2N 5W8", "2425-15 Northtown Way, Toronto, ON, M2N 7A2", "30 Chipping Road, Toronto, ON, M3B 1L1", "1501-18 Harrison Garden Boulevard, Toronto, ON, M2N 7J7", "710-75 W The Donway Way, Toronto, ON, M3C 2E9", "4 Silvergrove Road, Toronto, ON, M2L 2N6", "Lc3-18 Concorde Place, Toronto, ON, M3C 3T9", "303-801 E Lawrence Avenue, Toronto, ON, M3C 3W2", "R2-2-60 Pavane Linkway Boulevard, Toronto, ON, M3C 1A1", "904-160 Vanderhoof Avenue, Toronto, ON, M4G 0B7", "81 Whitehall Road, Toronto, ON, M4W 2C8", "Th07-101 Erskine Avenue, Toronto, ON, M4P 0C5", "4007-8 The Esplanade, Toronto, ON, M5E 0A6", "44 Summerhill Gardens, Toronto, ON, M4T 1B4", "3108-30 Roehampton Avenue, Toronto, ON, M4P 0B9", "4012-210 Victoria Street, Toronto, ON, M5B 2R3"], "link": ["/properties/E4513401/67-sylvan-avenue-toronto-on?page=7&search_id=toronto-on&search_type=property_browse", "/properties/W4565193/57-thirtieth-street-toronto-on?page=7&search_id=toronto-on&search_type=property_browse", "/properties/C4575829/29-tobruk-crescent-toronto-on?page=7&search_id=toronto-on&search_type=property_browse", "/properties/C4577240/2121-80-harrison-garden-boulevard-toronto-on?page=7&search_id=toronto-on&search_type=property_browse", "/properties/C4576757/382-ruth-avenue-toronto-on?page=7&search_id=toronto-on&search_type=property_browse", "/properties/C4576458/15-3180-e-bayview-avenue-toronto-on?page=7&search_id=toronto-on&search_type=property_browse", "/properties/C4577282/8-flaming-rose-way-toronto-on?page=7&search_id=toronto-on&search_type=property_browse", "/properties/C4577076/2425-15-northtown-way-toronto-on?page=7&search_id=toronto-on&search_type=property_browse", "/properties/C4575758/30-chipping-road-toronto-on?page=7&search_id=toronto-on&search_type=property_browse", "/properties/C4577257/1501-18-harrison-garden-boulevard-toronto-on?page=7&search_id=toronto-on&search_type=property_browse", "/properties/C4576246/710-75-w-the-donway-way-toronto-on?page=7&search_id=toronto-on&search_type=property_browse", "/properties/C4576332/4-silvergrove-road-toronto-on?page=7&search_id=toronto-on&search_type=property_browse", "/properties/C4576726/lc3-18-concorde-place-toronto-on?page=7&search_id=toronto-on&search_type=property_browse", "/properties/C4576667/303-801-e-lawrence-avenue-toronto-on?page=7&search_id=toronto-on&search_type=property_browse", "/properties/C4575865/r2-2-60-pavane-linkway-boulevard-toronto-on?page=7&search_id=toronto-on&search_type=property_browse", "/properties/C4575805/904-160-vanderhoof-avenue-toronto-on?page=7&search_id=toronto-on&search_type=property_browse", "/properties/C4575873/81-whitehall-road-toronto-on?page=7&search_id=toronto-on&search_type=property_browse", "/properties/C4576272/th07-101-erskine-avenue-toronto-on?page=7&search_id=toronto-on&search_type=property_browse", "/properties/C4575868/4007-8-the-esplanade-toronto-on?page=7&search_id=toronto-on&search_type=property_browse", "/properties/C4576827/44-summerhill-gardens-toronto-on?page=7&search_id=toronto-on&search_type=property_browse", "/properties/C4575901/3108-30-roehampton-avenue-toronto-on?page=7&search_id=toronto-on&search_type=property_browse", "/properties/C4577167/4012-210-victoria-street-toronto-on?page=7&search_id=toronto-on&search_type=property_browse"]},
{"price": ["\n$1,999,999\n", "\n$1,129,000\n", "\n$599,900\n", "\n$789,000\n", "\n$579,000\n", "\n$699,000\n", "\n$1,849,000\n", "\n$299,900\n", "\n$549,000\n", "\n$1,449,000\n", "\n$2,100,000\n", "\n$1,799,999\n", "\n$949,989\n", "\n$1,450,000\n", "\n$1,150,000\n", "\n$480,000\n", "\n$1,199,000\n", "\n$515,000\n", "\n$499,900\n", "\n$549,900\n", "\n$619,900\n", "\n$575,000\n"], "addr": ["67 Sylvan Avenue, Toronto, ON, M1M 1J9", "57 Thirtieth Street, Toronto, ON, M8W 3B7", "94 Bonis Avenue, Toronto, ON, M1T 2V2", "62-1075 Ellesmere Road, Toronto, ON, M1P 5C3", "Unit 5-647A Warden Avenue, Toronto, ON, M1L 0E7", "16 Lombardy Crescent, Toronto, ON, M1K 4N8", "17 Donmore Avenue, Toronto, ON, M4J 3V3", "704-665 Kennedy Road, Toronto, ON, M1K 5E2", "8-50 Mendelssohn Street, Toronto, ON, M1L 0G8", "224B Gledhill Avenue, Toronto, ON, M4C 5L1", "41 Kenilworth Avenue, Toronto, ON, M4L 3S4", "64 Holborne Avenue, Toronto, ON, M4C 2R1", "330 Sammon Avenue, Toronto, ON, M4J 2A3", "42 Whistle Post Street, Toronto, ON, M4E 3W8", "50 Wembley Drive, Toronto, ON, M4L 3E1", "2312-33 Singer Court, Toronto, ON, M2K 0B4", "255 Waverley Road, Toronto, ON, M4L 3T5", "221-52 Forest Manor Road, Toronto, ON, M2J 1M6", "205-60 Haslett Avenue, Toronto, ON, M4L 3R2", "Sph6-10 Northtown Way, Toronto, ON, M2N 7L4", "7 Log Fernway Out, Toronto, ON, M2J 4M7", "1510-120 Harrison Garden Boulevard, Toronto, ON, M2N 2T2"], "link": ["/properties/E4513401/67-sylvan-avenue-toronto-on?page=6&search_id=toronto-on&search_type=property_browse", "/properties/W4565193/57-thirtieth-street-toronto-on?page=6&search_id=toronto-on&search_type=property_browse", "/properties/E4577528/94-bonis-avenue-toronto-on?page=6&search_id=toronto-on&search_type=property_browse", "/properties/E4576181/62-1075-ellesmere-road-toronto-on?page=6&search_id=toronto-on&search_type=property_browse", "/properties/E4576178/unit-5-647a-warden-avenue-toronto-on?page=6&search_id=toronto-on&search_type=property_browse", "/properties/E4576859/16-lombardy-crescent-toronto-on?page=6&search_id=toronto-on&search_type=property_browse", "/properties/E4575816/17-donmore-avenue-toronto-on?page=6&search_id=toronto-on&search_type=property_browse", "/properties/E4577201/704-665-kennedy-road-toronto-on?page=6&search_id=toronto-on&search_type=property_browse", "/properties/E4577518/8-50-mendelssohn-street-toronto-on?page=6&search_id=toronto-on&search_type=property_browse", "/properties/E4576311/224b-gledhill-avenue-toronto-on?page=6&search_id=toronto-on&search_type=property_browse", "/properties/E4576088/41-kenilworth-avenue-toronto-on?page=6&search_id=toronto-on&search_type=property_browse", "/properties/E4576035/64-holborne-avenue-toronto-on?page=6&search_id=toronto-on&search_type=property_browse", "/properties/E4577177/330-sammon-avenue-toronto-on?page=6&search_id=toronto-on&search_type=property_browse", "/properties/E4577377/42-whistle-post-street-toronto-on?page=6&search_id=toronto-on&search_type=property_browse", "/properties/E4576672/50-wembley-drive-toronto-on?page=6&search_id=toronto-on&search_type=property_browse", "/properties/C4577137/2312-33-singer-court-toronto-on?page=6&search_id=toronto-on&search_type=property_browse", "/properties/E4575759/255-waverley-road-toronto-on?page=6&search_id=toronto-on&search_type=property_browse", "/properties/C4576036/221-52-forest-manor-road-toronto-on?page=6&search_id=toronto-on&search_type=property_browse", "/properties/E4575809/205-60-haslett-avenue-toronto-on?page=6&search_id=toronto-on&search_type=property_browse", "/properties/C4576177/sph6-10-northtown-way-toronto-on?page=6&search_id=toronto-on&search_type=property_browse", "/properties/C4577026/7-log-fernway-out-toronto-on?page=6&search_id=toronto-on&search_type=property_browse", "/properties/C4576937/1510-120-harrison-garden-boulevard-toronto-on?page=6&search_id=toronto-on&search_type=property_browse"]},
{"price": ["\n$829,900\n", "\n$1,999,999\n", "\n$1,100,000\n", "\n$779,000\n", "\n$699,900\n", "\n$1,350,000\n", "\n$639,000\n", "\n$1,950,000\n", "\n$990,000\n", "\n$780,000\n", "\n$565,000\n", "\n$719,000\n", "\n$595,000\n", "\n$434,000\n", "\n$599,900\n", "\n$699,900\n", "\n$445,000\n", "\n$370,000\n", "\n$749,900\n", "\n$938,800\n", "\n$415,000\n", "\n$599,000\n"], "addr": ["28 Medley Crescent, Toronto, ON, M1J 1Y3", "67 Sylvan Avenue, Toronto, ON, M1M 1J9", "265 Kane Avenue, Toronto, ON, M6M 3N8", "16 Jillson Avenue, Toronto, ON, M6S 2P4", "20 Crow Tr, Toronto, ON, M1B 1X4", "88 Franklin Avenue, Toronto, ON, M6P 3Y8", "15 Whispering Willow Ptwy, Toronto, ON, M1B 4A8", "24 Riverside Crescent, Toronto, ON, M6S 1B6", "15 Rolling Meadows, Toronto, ON, M1C 1X8", "41 Oakley Boulevard, Toronto, ON, M1P 3P5", "13-25 Heron Park Place, Toronto, ON, M1E 0B8", "213 Andona Crescent, Toronto, ON, M1C 5J8", "119 Nelson Street, Toronto, ON, M1J 2W1", "615-36 Lee Centre Drive, Toronto, ON, M1H 3K2", "88 Painted Post Drive, Toronto, ON, M1H 1T4", "10 Glenda Road, Toronto, ON, M1M 2H4", "112-50 Scarborough Golf Clu Road, Toronto, ON, M1M 3T5", "1606-121 Trudelle Street, Toronto, ON, M1J 3K4", "30 Bimbrok Road, Toronto, ON, M1K 4T7", "1 Lockdare Street, Toronto, ON, M1S 2Z5", "1811-2050 Bridletowne Circ, Toronto, ON, M1W 2V5", "5-2051 Bridletowne Circ, Toronto, ON, M1W 2J7"], "link": ["/properties/E4546454/28-medley-crescent-toronto-on?page=5&search_id=toronto-on&search_type=property_browse", "/properties/E4513401/67-sylvan-avenue-toronto-on?page=5&search_id=toronto-on&search_type=property_browse", "/properties/W4577251/265-kane-avenue-toronto-on?page=5&search_id=toronto-on&search_type=property_browse", "/properties/W4576773/16-jillson-avenue-toronto-on?page=5&search_id=toronto-on&search_type=property_browse", "/properties/E4576504/20-crow-tr-toronto-on?page=5&search_id=toronto-on&search_type=property_browse", "/properties/W4576148/88-franklin-avenue-toronto-on?page=5&search_id=toronto-on&search_type=property_browse", "/properties/E4577273/15-whispering-willow-ptwy-toronto-on?page=5&search_id=toronto-on&search_type=property_browse", "/properties/W4577041/24-riverside-crescent-toronto-on?page=5&search_id=toronto-on&search_type=property_browse", "/properties/E4576072/15-rolling-meadows-toronto-on?page=5&search_id=toronto-on&search_type=property_browse", "/properties/E4575821/41-oakley-boulevard-toronto-on?page=5&search_id=toronto-on&search_type=property_browse", "/properties/E4577403/13-25-heron-park-place-toronto-on?page=5&search_id=toronto-on&search_type=property_browse", "/properties/E4576474/213-andona-crescent-toronto-on?page=5&search_id=toronto-on&search_type=property_browse", "/properties/E4577049/119-nelson-street-toronto-on?page=5&search_id=toronto-on&search_type=property_browse", "/properties/E4575994/615-36-lee-centre-drive-toronto-on?page=5&search_id=toronto-on&search_type=property_browse", "/properties/E4577063/88-painted-post-drive-toronto-on?page=5&search_id=toronto-on&search_type=property_browse", "/properties/E4576681/10-glenda-road-toronto-on?page=5&search_id=toronto-on&search_type=property_browse", "/properties/E4576287/112-50-scarborough-golf-clu-road-toronto-on?page=5&search_id=toronto-on&search_type=property_browse", "/properties/E4577394/1606-121-trudelle-street-toronto-on?page=5&search_id=toronto-on&search_type=property_browse", "/properties/E4576934/30-bimbrok-road-toronto-on?page=5&search_id=toronto-on&search_type=property_browse", "/properties/E4577068/1-lockdare-street-toronto-on?page=5&search_id=toronto-on&search_type=property_browse", "/properties/E4575861/1811-2050-bridletowne-circ-toronto-on?page=5&search_id=toronto-on&search_type=property_browse", "/properties/E4576153/5-2051-bridletowne-circ-toronto-on?page=5&search_id=toronto-on&search_type=property_browse"]},
{"price": ["\n$1,949,000\n", "\n$829,900\n", "\n$529,000\n", "\n$1,999,000\n", "\n$1,095,000\n", "\n$2,375,000\n", "\n$989,900\n", "\n$1,179,000\n", "\n$934,900\n", "\n$799,000\n", "\n$885,000\n", "\n$779,900\n", "\n$259,000\n", "\n$499,000\n", "\n$575,000\n", "\n$899,900\n", "\n$649,800\n", "\n$449,900\n", "\n$497,000\n", "\n$759,900\n", "\n$749,900\n", "\n$1,888,000\n"], "addr": ["5 Broadmead Avenue, Toronto, ON, M1M 1C3", "28 Medley Crescent, Toronto, ON, M1J 1Y3", "125-34 N Fieldway Road, Toronto, ON, M8Z 0E3", "76 West Deane Park Drive, Toronto, ON, M9B 2S3", "10 Beaver Bend Crescent, Toronto, ON, M9B 5P8", "12 Cronin Drive, Toronto, ON, M9B 4T8", "40 Dimplefield Place, Toronto, ON, M9C 4A1", "21 Mcintosh Avenue, Toronto, ON, M8Y 3E1", "61 Mulgrove Drive, Toronto, ON, M9C 2R4", "202 Aldercrest Road, Toronto, ON, M8W 4J4", "3-140 Long Branch Avenue, Toronto, ON, M8W 0B1", "Toronto, ON", "1007-3 Marine Parade Drive, Toronto, ON, M8V 3Z5", "1037-55 George Appleton Way, Toronto, ON, M3M 0A2", "705-15 James Finlay Way, Toronto, ON, M3M 0B3", "1 Bunnell Crescent, Toronto, ON, M3M 2B8", "247 Torbarrie Road, Toronto, ON, M3L 0E2", "803-1070 W Sheppard Avenue, Toronto, ON, M3J 0G8", "#1217-1070 Sheppard Avenue, Toronto, ON, M3J 0G8", "412-250 Scarlett Road, Toronto, ON, M6N 4X5", "101 Lonborough Avenue, Toronto, ON, M6M 1X7", "348 Maple Leaf Drive, Toronto, ON, M6L 1P6"], "link": ["/properties/E4554867/5-broadmead-avenue-toronto-on?page=4&search_id=toronto-on&search_type=property_browse", "/properties/E4546454/28-medley-crescent-toronto-on?page=4&search_id=toronto-on&search_type=property_browse", "/properties/W4575888/125-34-n-fieldway-road-toronto-on?page=4&search_id=toronto-on&search_type=property_browse", "/properties/W4576251/76-west-deane-park-drive-toronto-on?page=4&search_id=toronto-on&search_type=property_browse", "/properties/W4576260/10-beaver-bend-crescent-toronto-on?page=4&search_id=toronto-on&search_type=property_browse", "/properties/W4576609/12-cronin-drive-toronto-on?page=4&search_id=toronto-on&search_type=property_browse", "/properties/W4576057/40-dimplefield-place-toronto-on?page=4&search_id=toronto-on&search_type=property_browse", "/properties/W4575908/21-mcintosh-avenue-toronto-on?page=4&search_id=toronto-on&search_type=property_browse", "/properties/W4576207/61-mulgrove-drive-toronto-on?page=4&search_id=toronto-on&search_type=property_browse", "/properties/W4576085/202-aldercrest-road-toronto-on?page=4&search_id=toronto-on&search_type=property_browse", "/properties/W4575824/3-140-long-branch-avenue-toronto-on?page=4&search_id=toronto-on&search_type=property_browse", "/properties/W4577088/toronto-on?page=4&search_id=toronto-on&search_type=property_browse", "/properties/W4576868/1007-3-marine-parade-drive-toronto-on?page=4&search_id=toronto-on&search_type=property_browse", "/properties/W4577237/1037-55-george-appleton-way-toronto-on?page=4&search_id=toronto-on&search_type=property_browse", "/properties/W4576654/705-15-james-finlay-way-toronto-on?page=4&search_id=toronto-on&search_type=property_browse", "/properties/W4576887/1-bunnell-crescent-toronto-on?page=4&search_id=toronto-on&search_type=property_browse", "/properties/W4576146/247-torbarrie-road-toronto-on?page=4&search_id=toronto-on&search_type=property_browse", "/properties/W4575866/803-1070-w-sheppard-avenue-toronto-on?page=4&search_id=toronto-on&search_type=property_browse", "/properties/W4575795/1217-1070-sheppard-avenue-toronto-on?page=4&search_id=toronto-on&search_type=property_browse", "/properties/W4576972/412-250-scarlett-road-toronto-on?page=4&search_id=toronto-on&search_type=property_browse", "/properties/W4576123/101-lonborough-avenue-toronto-on?page=4&search_id=toronto-on&search_type=property_browse", "/properties/W4576262/348-maple-leaf-drive-toronto-on?page=4&search_id=toronto-on&search_type=property_browse"]},
{"price": ["\n$1,949,000\n", "\n$829,900\n", "\n$960,000\n", "\n$580,000\n", "\n$1,099,900\n", "\n$599,000\n", "\n$630,000\n", "\n$495,000\n", "\n$529,000\n", "\n$469,999\n", "\n$729,800\n", "\n$405,000\n", "\n$699,000\n", "\n$699,999\n", "\n$899,000\n", "\n$1,299,000\n", "\n$410,000\n", "\n$719,000\n", "\n$569,000\n", "\n$1,299,000\n", "\n$749,000\n", "\n$12,800,000\n"], "addr": ["5 Broadmead Avenue, Toronto, ON, M1M 1C3", "28 Medley Crescent, Toronto, ON, M1J 1Y3", "1206-32 Davenport Road, Toronto, ON, M5R 1H3", "2608-57 St. Joseph Street, Toronto, ON, M5S 2Y1", "306-2010 Islington Avenue, Toronto, ON, M9P 3S8", "505-50 Forest Manor Road, Toronto, ON, M2J 1M6", "705-260 Scarlett Road, Toronto, ON, M6N 4X6", "3420-30 Shore Breeze Drive, Toronto, ON, M8V 0J1", "2612-30 Shore Breeze Drive, Toronto, ON, M8V 0J1", "43-10 Rodda Boulevard, Toronto, ON, M1E 2Z6", "23-145 Long Branch Avenue, Toronto, ON, M8W 0A9", "1113-18 Lee Centre Drive, Toronto, ON, M1H 3H5", "Th05-23 W Sheppard Avenue, Toronto, ON, M2N 0C8", "213-21 Olive Avenue, Toronto, ON, M2N 4N4", "93 Billings Avenue, Toronto, ON, M4L 2S3", "27 Topbank Drive, Toronto, ON, M9W 7C2", "608-238 Albion Road, Toronto, ON, M9W 6A7", "20 Snaresbrook Drive, Toronto, ON, M9W 2N4", "513-9 Michael Power Place, Toronto, ON, M9A 0A5", "20 Downpatrick Crescent, Toronto, ON, M9R 4A4", "97 S Monterrey Drive, Toronto, ON, M9V 1T2", "65 Kingsway Crescent, Toronto, ON, M8X 2R5"], "link": ["/properties/E4554867/5-broadmead-avenue-toronto-on?page=3&search_id=toronto-on&search_type=property_browse", "/properties/E4546454/28-medley-crescent-toronto-on?page=3&search_id=toronto-on&search_type=property_browse", "/properties/C4577648/1206-32-davenport-road-toronto-on?page=3&search_id=toronto-on&search_type=property_browse", "/properties/C4577665/2608-57-st-joseph-street-toronto-on?page=3&search_id=toronto-on&search_type=property_browse", "/properties/W4576935/306-2010-islington-avenue-toronto-on?page=3&search_id=toronto-on&search_type=property_browse", "/properties/C4577633/505-50-forest-manor-road-toronto-on?page=3&search_id=toronto-on&search_type=property_browse", "/properties/W4577636/705-260-scarlett-road-toronto-on?page=3&search_id=toronto-on&search_type=property_browse", "/properties/W4577571/3420-30-shore-breeze-drive-toronto-on?page=3&search_id=toronto-on&search_type=property_browse", "/properties/W4577573/2612-30-shore-breeze-drive-toronto-on?page=3&search_id=toronto-on&search_type=property_browse", "/properties/E4577567/43-10-rodda-boulevard-toronto-on?page=3&search_id=toronto-on&search_type=property_browse", "/properties/W4577552/23-145-long-branch-avenue-toronto-on?page=3&search_id=toronto-on&search_type=property_browse", "/properties/E4577554/1113-18-lee-centre-drive-toronto-on?page=3&search_id=toronto-on&search_type=property_browse", "/properties/C4577539/th05-23-w-sheppard-avenue-toronto-on?page=3&search_id=toronto-on&search_type=property_browse", "/properties/C4577548/213-21-olive-avenue-toronto-on?page=3&search_id=toronto-on&search_type=property_browse", "/properties/E4577561/93-billings-avenue-toronto-on?page=3&search_id=toronto-on&search_type=property_browse", "/properties/W4576183/27-topbank-drive-toronto-on?page=3&search_id=toronto-on&search_type=property_browse", "/properties/W4577492/608-238-albion-road-toronto-on?page=3&search_id=toronto-on&search_type=property_browse", "/properties/W4575876/20-snaresbrook-drive-toronto-on?page=3&search_id=toronto-on&search_type=property_browse", "/properties/W4576487/513-9-michael-power-place-toronto-on?page=3&search_id=toronto-on&search_type=property_browse", "/properties/W4576119/20-downpatrick-crescent-toronto-on?page=3&search_id=toronto-on&search_type=property_browse", "/properties/W4575978/97-s-monterrey-drive-toronto-on?page=3&search_id=toronto-on&search_type=property_browse", "/properties/W4577046/65-kingsway-crescent-toronto-on?page=3&search_id=toronto-on&search_type=property_browse"]},
{"price": ["\n$829,900\n", "\n$1,129,000\n", "\n$980,000\n", "\n$689,887\n", "\n$858,800\n", "\n$1,799,000\n", "\n$829,900\n", "\n$1,499,900\n", "\n$1,999,999\n", "\n$2,498,000\n", "\n$999,000\n", "\n$1,547,000\n", "\n$649,000\n", "\n$1,325,000\n", "\n$2,200,000\n", "\n$1,318,000\n", "\n$1,999,888\n", "\n$996,000\n", "\n$949,900\n", "\n$439,900\n", "\n$770,000\n", "\n$899,000\n"], "addr": ["28 Medley Crescent, Toronto, ON, M1J 1Y3", "57 Thirtieth Street, Toronto, ON, M8W 3B7", "2106-2121 W Lake Shore Boulevard, Toronto, ON, M8V 4E9", "508-155 Yorkville Avenue, Toronto, ON, M4W 0A4", "31 Lysander Court, Toronto, ON, M1V 3R2", "76 E Caribou Road, Toronto, ON, M5N 2A8", "28 Medley Crescent, Toronto, ON, M1J 1Y3", "16 Newbury Lane, Toronto, ON, M3H 1H5", "67 Sylvan Avenue, Toronto, ON, M1M 1J9", "62 Chatsworth Drive, Toronto, ON, M4R 1R7", "65 Maughan Crescent, Toronto, ON, M4L 3E6", "30 Kenny Avenue, Toronto, ON, M8Z 3R2", "58 Lacey Avenue, Toronto, ON, M6M 3L7", "24 Westdale Drive, Toronto, ON, M3K 1A5", "38 Beresford Avenue, Toronto, ON, M6S 3A8", "191 Hallam Street, Toronto, ON, M6H 1X4", "61 Ridgepoint Crescent, Toronto, ON, M6M 2Z7", "7-265 Van Dusen Boulevard, Toronto, ON, M8Z 3J2", "497 Jones Avenue, Toronto, ON, M4J 3G8", "229-3765 E Sheppard Avenue, Toronto, ON, M1T 3R7", "502-377 Madison Avenue, Toronto, ON, M4V 2W7", "1908-2 Anndale Avenue, Toronto, ON, M2N 0G5"], "link": ["/properties/E4546454/28-medley-crescent-toronto-on?page=2&search_id=toronto-on&search_type=property_browse", "/properties/W4565193/57-thirtieth-street-toronto-on?page=2&search_id=toronto-on&search_type=property_browse", "/properties/W4551866/2106-2121-w-lake-shore-boulevard-toronto-on?page=2&search_id=toronto-on&search_type=property_browse", "/properties/C4551503/508-155-yorkville-avenue-toronto-on?page=2&search_id=toronto-on&search_type=property_browse", "/properties/E4549366/31-lysander-court-toronto-on?page=2&search_id=toronto-on&search_type=property_browse", "/properties/C4547101/76-e-caribou-road-toronto-on?page=2&search_id=toronto-on&search_type=property_browse", "/properties/E4546454/28-medley-crescent-toronto-on?page=2&search_id=toronto-on&search_type=property_browse", "/properties/C4517834/16-newbury-lane-toronto-on?page=2&search_id=toronto-on&search_type=property_browse", "/properties/E4513401/67-sylvan-avenue-toronto-on?page=2&search_id=toronto-on&search_type=property_browse", "/properties/C4499747/62-chatsworth-drive-toronto-on?page=2&search_id=toronto-on&search_type=property_browse", "/properties/E4317669/65-maughan-crescent-toronto-on?page=2&search_id=toronto-on&search_type=property_browse", "/properties/W4577638/30-kenny-avenue-toronto-on?page=2&search_id=toronto-on&search_type=property_browse", "/properties/W4577799/58-lacey-avenue-toronto-on?page=2&search_id=toronto-on&search_type=property_browse", "/properties/W4577769/24-westdale-drive-toronto-on?page=2&search_id=toronto-on&search_type=property_browse", "/properties/W4577733/38-beresford-avenue-toronto-on?page=2&search_id=toronto-on&search_type=property_browse", "/properties/W4577686/191-hallam-street-toronto-on?page=2&search_id=toronto-on&search_type=property_browse", "/properties/W4577690/61-ridgepoint-crescent-toronto-on?page=2&search_id=toronto-on&search_type=property_browse", "/properties/W4577668/7-265-van-dusen-boulevard-toronto-on?page=2&search_id=toronto-on&search_type=property_browse", "/properties/E4577694/497-jones-avenue-toronto-on?page=2&search_id=toronto-on&search_type=property_browse", "/properties/E4577724/229-3765-e-sheppard-avenue-toronto-on?page=2&search_id=toronto-on&search_type=property_browse", "/properties/C4577776/502-377-madison-avenue-toronto-on?page=2&search_id=toronto-on&search_type=property_browse", "/properties/C4577693/1908-2-anndale-avenue-toronto-on?page=2&search_id=toronto-on&search_type=property_browse"]}
]